{
  "arm": "b_heads",
  "tier": 3,
  "seed": 1,
  "toy": "hetero",
  "n_train": 200,
  "n_test": 500,
  "sigma": 0.15,
  "w_max": 12,
  "convergence": {
    "1": {
      "converged": true,
      "hit_cap": false,
      "trustworthy": true,
      "still_improving_at_stop": false,
      "diverged": false,
      "stop_epoch": 6500,
      "best_val": 4.871077537536621,
      "best_epoch": 500,
      "recent_improvement": -0.0036072731018066406,
      "trajectory": [
        [
          500,
          4.871077537536621
        ],
        [
          1000,
          4.894168376922607
        ],
        [
          1500,
          4.911741733551025
        ],
        [
          2000,
          4.905902862548828
        ],
        [
          2500,
          4.998091697692871
        ],
        [
          3000,
          5.067442893981934
        ],
        [
          3500,
          5.069760322570801
        ],
        [
          4000,
          5.0664873123168945
        ],
        [
          4500,
          5.062612056732178
        ],
        [
          5000,
          5.076894283294678
        ],
        [
          5500,
          5.078444004058838
        ],
        [
          6000,
          5.065184593200684
        ],
        [
          6500,
          5.050951957702637
        ],
        [
          7000,
          5.067872047424316
        ],
        [
          7500,
          5.052487373352051
        ],
        [
          8000,
          5.073366641998291
        ],
        [
          8500,
          5.060778617858887
        ],
        [
          9000,
          5.066534519195557
        ],
        [
          9500,
          5.039964199066162
        ],
        [
          10000,
          5.073297500610352
        ],
        [
          10500,
          5.073605537414551
        ],
        [
          11000,
          5.063285827636719
        ],
        [
          11500,
          5.05989933013916
        ],
        [
          12000,
          5.05308723449707
        ],
        [
          12500,
          5.076298713684082
        ],
        [
          13000,
          5.0547590255737305
        ],
        [
          13500,
          5.065617561340332
        ],
        [
          14000,
          5.064511299133301
        ],
        [
          14500,
          5.062778472900391
        ],
        [
          15000,
          5.061883449554443
        ],
        [
          15500,
          5.067776203155518
        ],
        [
          16000,
          5.054770469665527
        ],
        [
          16500,
          5.0649614334106445
        ],
        [
          17000,
          5.069044589996338
        ],
        [
          17500,
          5.05356502532959
        ],
        [
          18000,
          5.051077842712402
        ],
        [
          18500,
          5.0495195388793945
        ],
        [
          19000,
          5.045544624328613
        ],
        [
          19500,
          5.0587077140808105
        ],
        [
          20000,
          5.075718879699707
        ],
        [
          20500,
          5.0470685958862305
        ],
        [
          21000,
          5.063112735748291
        ],
        [
          21500,
          5.061130523681641
        ],
        [
          22000,
          5.060051918029785
        ],
        [
          22500,
          5.058500289916992
        ],
        [
          23000,
          5.071410655975342
        ],
        [
          23500,
          5.0430498123168945
        ],
        [
          24000,
          5.067950248718262
        ],
        [
          24500,
          5.055445194244385
        ],
        [
          25000,
          5.065604209899902
        ],
        [
          25500,
          5.0391154289245605
        ],
        [
          26000,
          5.0624871253967285
        ],
        [
          26500,
          5.064879417419434
        ],
        [
          27000,
          5.050433158874512
        ],
        [
          27500,
          5.055358409881592
        ],
        [
          28000,
          5.0472307205200195
        ],
        [
          28500,
          5.059471607208252
        ],
        [
          29000,
          5.070927143096924
        ],
        [
          29500,
          5.058086395263672
        ],
        [
          30000,
          5.04695987701416
        ],
        [
          30500,
          5.063225269317627
        ],
        [
          31000,
          5.067597389221191
        ],
        [
          31500,
          5.0686516761779785
        ],
        [
          32000,
          5.0575456619262695
        ],
        [
          32500,
          5.060369968414307
        ],
        [
          33000,
          5.054989337921143
        ],
        [
          33500,
          5.059259414672852
        ],
        [
          34000,
          5.051839351654053
        ],
        [
          34500,
          5.0520734786987305
        ],
        [
          35000,
          5.06424617767334
        ],
        [
          35500,
          5.073583126068115
        ],
        [
          36000,
          5.061885356903076
        ],
        [
          36500,
          5.062888145446777
        ],
        [
          37000,
          5.050136566162109
        ],
        [
          37500,
          5.062362194061279
        ],
        [
          38000,
          5.046248912811279
        ],
        [
          38500,
          5.044163703918457
        ],
        [
          39000,
          5.070950508117676
        ],
        [
          39500,
          5.068532943725586
        ],
        [
          40000,
          5.046773433685303
        ],
        [
          40500,
          5.055581569671631
        ],
        [
          41000,
          5.051048278808594
        ],
        [
          41500,
          5.055474281311035
        ],
        [
          42000,
          5.056453704833984
        ],
        [
          42500,
          5.041609287261963
        ],
        [
          43000,
          5.058922290802002
        ],
        [
          43500,
          5.049117565155029
        ],
        [
          44000,
          5.069538593292236
        ],
        [
          44500,
          5.068176746368408
        ],
        [
          45000,
          5.053697109222412
        ],
        [
          45500,
          5.040069580078125
        ],
        [
          46000,
          5.0443434715271
        ],
        [
          46500,
          5.0586838722229
        ],
        [
          47000,
          5.057372093200684
        ],
        [
          47500,
          5.056722640991211
        ],
        [
          48000,
          5.071588516235352
        ],
        [
          48500,
          5.05807638168335
        ],
        [
          49000,
          5.065905570983887
        ],
        [
          49500,
          5.050250053405762
        ],
        [
          50000,
          5.059064865112305
        ],
        [
          50500,
          5.064434051513672
        ],
        [
          51000,
          5.053078651428223
        ],
        [
          51500,
          5.067170143127441
        ],
        [
          52000,
          5.047950744628906
        ]
      ]
    },
    "2": {
      "converged": true,
      "hit_cap": false,
      "trustworthy": true,
      "still_improving_at_stop": false,
      "diverged": false,
      "stop_epoch": 52000,
      "best_val": 3.9354496002197266,
      "best_epoch": 46000,
      "recent_improvement": -0.05545377731323242,
      "trajectory": [
        [
          500,
          4.893599510192871
        ],
        [
          1000,
          4.849152565002441
        ],
        [
          1500,
          4.853137016296387
        ],
        [
          2000,
          4.917559623718262
        ],
        [
          2500,
          5.000216484069824
        ],
        [
          3000,
          4.931515693664551
        ],
        [
          3500,
          4.785627841949463
        ],
        [
          4000,
          4.5790114402771
        ],
        [
          4500,
          4.506103515625
        ],
        [
          5000,
          4.354056358337402
        ],
        [
          5500,
          4.324672222137451
        ],
        [
          6000,
          4.37611722946167
        ],
        [
          6500,
          4.280900478363037
        ],
        [
          7000,
          4.284555912017822
        ],
        [
          7500,
          4.187526226043701
        ],
        [
          8000,
          4.212121963500977
        ],
        [
          8500,
          4.219460487365723
        ],
        [
          9000,
          4.179687976837158
        ],
        [
          9500,
          4.114352226257324
        ],
        [
          10000,
          4.18209171295166
        ],
        [
          10500,
          4.127222537994385
        ],
        [
          11000,
          4.090930938720703
        ],
        [
          11500,
          4.125916481018066
        ],
        [
          12000,
          4.091994762420654
        ],
        [
          12500,
          4.072044372558594
        ],
        [
          13000,
          4.066977500915527
        ],
        [
          13500,
          4.065328121185303
        ],
        [
          14000,
          4.077406883239746
        ],
        [
          14500,
          4.086985111236572
        ],
        [
          15000,
          4.04221773147583
        ],
        [
          15500,
          4.067031383514404
        ],
        [
          16000,
          4.049213886260986
        ],
        [
          16500,
          4.046957969665527
        ],
        [
          17000,
          4.0690836906433105
        ],
        [
          17500,
          4.041569232940674
        ],
        [
          18000,
          4.066099166870117
        ],
        [
          18500,
          4.07041597366333
        ],
        [
          19000,
          4.030704021453857
        ],
        [
          19500,
          4.033360481262207
        ],
        [
          20000,
          4.033098220825195
        ],
        [
          20500,
          4.005215644836426
        ],
        [
          21000,
          4.025489330291748
        ],
        [
          21500,
          4.064143657684326
        ],
        [
          22000,
          4.030701160430908
        ],
        [
          22500,
          4.039026260375977
        ],
        [
          23000,
          4.037744998931885
        ],
        [
          23500,
          4.017177104949951
        ],
        [
          24000,
          4.046659469604492
        ],
        [
          24500,
          4.001986503601074
        ],
        [
          25000,
          4.023106575012207
        ],
        [
          25500,
          4.0287933349609375
        ],
        [
          26000,
          4.022246837615967
        ],
        [
          26500,
          4.042562484741211
        ],
        [
          27000,
          4.043652534484863
        ],
        [
          27500,
          4.0193305015563965
        ],
        [
          28000,
          3.997375965118408
        ],
        [
          28500,
          4.018399238586426
        ],
        [
          29000,
          4.025147438049316
        ],
        [
          29500,
          4.035007953643799
        ],
        [
          30000,
          4.056214332580566
        ],
        [
          30500,
          4.035470485687256
        ],
        [
          31000,
          3.9933791160583496
        ],
        [
          31500,
          4.031566619873047
        ],
        [
          32000,
          4.021512508392334
        ],
        [
          32500,
          4.014441013336182
        ],
        [
          33000,
          4.003787994384766
        ],
        [
          33500,
          3.9854347705841064
        ],
        [
          34000,
          4.032533645629883
        ],
        [
          34500,
          4.011809825897217
        ],
        [
          35000,
          4.00868034362793
        ],
        [
          35500,
          3.988137722015381
        ],
        [
          36000,
          4.073645114898682
        ],
        [
          36500,
          4.022448539733887
        ],
        [
          37000,
          3.9936165809631348
        ],
        [
          37500,
          4.021149635314941
        ],
        [
          38000,
          4.0013885498046875
        ],
        [
          38500,
          3.9785194396972656
        ],
        [
          39000,
          3.9841277599334717
        ],
        [
          39500,
          4.045700550079346
        ],
        [
          40000,
          3.9898815155029297
        ],
        [
          40500,
          4.040478229522705
        ],
        [
          41000,
          3.998359203338623
        ],
        [
          41500,
          4.027984619140625
        ],
        [
          42000,
          4.008320331573486
        ],
        [
          42500,
          4.006903648376465
        ],
        [
          43000,
          4.008209228515625
        ],
        [
          43500,
          4.024794578552246
        ],
        [
          44000,
          3.981471538543701
        ],
        [
          44500,
          3.951507091522217
        ],
        [
          45000,
          3.993143081665039
        ],
        [
          45500,
          3.9852194786071777
        ],
        [
          46000,
          3.9354496002197266
        ],
        [
          46500,
          3.9960315227508545
        ],
        [
          47000,
          4.022225379943848
        ],
        [
          47500,
          3.9922027587890625
        ],
        [
          48000,
          4.05823278427124
        ],
        [
          48500,
          3.996887683868408
        ],
        [
          49000,
          3.9798598289489746
        ],
        [
          49500,
          4.018531799316406
        ],
        [
          50000,
          4.015975475311279
        ],
        [
          50500,
          4.041521072387695
        ],
        [
          51000,
          4.054401397705078
        ],
        [
          51500,
          4.038788318634033
        ],
        [
          52000,
          3.990903377532959
        ]
      ]
    },
    "3": {
      "converged": true,
      "hit_cap": false,
      "trustworthy": true,
      "still_improving_at_stop": false,
      "diverged": false,
      "stop_epoch": 27000,
      "best_val": 3.9552242755889893,
      "best_epoch": 46000,
      "recent_improvement": -0.05945181846618652,
      "trajectory": [
        [
          500,
          4.875546932220459
        ],
        [
          1000,
          4.8286943435668945
        ],
        [
          1500,
          4.788154602050781
        ],
        [
          2000,
          4.905988693237305
        ],
        [
          2500,
          4.9925360679626465
        ],
        [
          3000,
          4.840114593505859
        ],
        [
          3500,
          4.723092079162598
        ],
        [
          4000,
          4.5277814865112305
        ],
        [
          4500,
          4.455799102783203
        ],
        [
          5000,
          4.341507911682129
        ],
        [
          5500,
          4.332774639129639
        ],
        [
          6000,
          4.316159248352051
        ],
        [
          6500,
          4.288122653961182
        ],
        [
          7000,
          4.213643550872803
        ],
        [
          7500,
          4.169644355773926
        ],
        [
          8000,
          4.208577632904053
        ],
        [
          8500,
          4.199198246002197
        ],
        [
          9000,
          4.1825127601623535
        ],
        [
          9500,
          4.093813896179199
        ],
        [
          10000,
          4.191378116607666
        ],
        [
          10500,
          4.115462303161621
        ],
        [
          11000,
          4.12344217300415
        ],
        [
          11500,
          4.111137390136719
        ],
        [
          12000,
          4.078199863433838
        ],
        [
          12500,
          4.071471691131592
        ],
        [
          13000,
          4.079826354980469
        ],
        [
          13500,
          4.08205509185791
        ],
        [
          14000,
          4.058964252471924
        ],
        [
          14500,
          4.091506481170654
        ],
        [
          15000,
          4.060255527496338
        ],
        [
          15500,
          4.042088508605957
        ],
        [
          16000,
          4.046408653259277
        ],
        [
          16500,
          4.048519134521484
        ],
        [
          17000,
          4.063243389129639
        ],
        [
          17500,
          4.013464450836182
        ],
        [
          18000,
          4.05421781539917
        ],
        [
          18500,
          4.0824456214904785
        ],
        [
          19000,
          4.011903285980225
        ],
        [
          19500,
          4.0438947677612305
        ],
        [
          20000,
          4.022942543029785
        ],
        [
          20500,
          4.00456428527832
        ],
        [
          21000,
          3.9961464405059814
        ],
        [
          21500,
          4.038740634918213
        ],
        [
          22000,
          4.015712738037109
        ],
        [
          22500,
          4.048363208770752
        ],
        [
          23000,
          4.027253150939941
        ],
        [
          23500,
          4.044995307922363
        ],
        [
          24000,
          4.019783973693848
        ],
        [
          24500,
          4.0210065841674805
        ],
        [
          25000,
          3.9981296062469482
        ],
        [
          25500,
          4.00471305847168
        ],
        [
          26000,
          4.003105163574219
        ],
        [
          26500,
          4.0022196769714355
        ],
        [
          27000,
          4.0314106941223145
        ],
        [
          27500,
          4.005467414855957
        ],
        [
          28000,
          3.9974498748779297
        ],
        [
          28500,
          3.988096237182617
        ],
        [
          29000,
          3.9932150840759277
        ],
        [
          29500,
          4.024140357971191
        ],
        [
          30000,
          4.021206855773926
        ],
        [
          30500,
          4.042064666748047
        ],
        [
          31000,
          4.022058010101318
        ],
        [
          31500,
          4.006351470947266
        ],
        [
          32000,
          3.990969181060791
        ],
        [
          32500,
          4.012471675872803
        ],
        [
          33000,
          3.9940860271453857
        ],
        [
          33500,
          3.998966693878174
        ],
        [
          34000,
          4.014735698699951
        ],
        [
          34500,
          3.9903156757354736
        ],
        [
          35000,
          4.02161169052124
        ],
        [
          35500,
          4.006848335266113
        ],
        [
          36000,
          3.9980416297912598
        ],
        [
          36500,
          4.01414155960083
        ],
        [
          37000,
          4.002243995666504
        ],
        [
          37500,
          4.007874488830566
        ],
        [
          38000,
          4.00642204284668
        ],
        [
          38500,
          3.984804630279541
        ],
        [
          39000,
          3.9868245124816895
        ],
        [
          39500,
          4.012380123138428
        ],
        [
          40000,
          3.9930739402770996
        ],
        [
          40500,
          4.027718544006348
        ],
        [
          41000,
          3.9863181114196777
        ],
        [
          41500,
          4.004460334777832
        ],
        [
          42000,
          4.008498191833496
        ],
        [
          42500,
          3.9746041297912598
        ],
        [
          43000,
          4.003737926483154
        ],
        [
          43500,
          4.029962539672852
        ],
        [
          44000,
          3.9915618896484375
        ],
        [
          44500,
          4.0195393562316895
        ],
        [
          45000,
          3.9943089485168457
        ],
        [
          45500,
          4.009461402893066
        ],
        [
          46000,
          3.9552242755889893
        ],
        [
          46500,
          4.003896713256836
        ],
        [
          47000,
          3.9891750812530518
        ],
        [
          47500,
          3.9796230792999268
        ],
        [
          48000,
          4.013889789581299
        ],
        [
          48500,
          3.9940152168273926
        ],
        [
          49000,
          3.994614362716675
        ],
        [
          49500,
          4.005627155303955
        ],
        [
          50000,
          4.008373737335205
        ],
        [
          50500,
          4.0255022048950195
        ],
        [
          51000,
          3.9801230430603027
        ],
        [
          51500,
          4.002134799957275
        ],
        [
          52000,
          4.014676094055176
        ]
      ]
    },
    "4": {
      "converged": true,
      "hit_cap": false,
      "trustworthy": false,
      "still_improving_at_stop": false,
      "diverged": true,
      "stop_epoch": 11000,
      "best_val": 2.338287353515625,
      "best_epoch": 5000,
      "recent_improvement": -0.011706829071044922,
      "trajectory": [
        [
          500,
          4.857691764831543
        ],
        [
          1000,
          4.867997646331787
        ],
        [
          1500,
          4.950544834136963
        ],
        [
          2000,
          4.537130832672119
        ],
        [
          2500,
          3.272604465484619
        ],
        [
          3000,
          2.4166312217712402
        ],
        [
          3500,
          2.523451328277588
        ],
        [
          4000,
          2.414512872695923
        ],
        [
          4500,
          2.424384355545044
        ],
        [
          5000,
          2.338287353515625
        ],
        [
          5500,
          2.4303765296936035
        ],
        [
          6000,
          2.4834847450256348
        ],
        [
          6500,
          2.4637808799743652
        ],
        [
          7000,
          2.5505435466766357
        ],
        [
          7500,
          2.6461591720581055
        ],
        [
          8000,
          2.5659329891204834
        ],
        [
          8500,
          2.662827968597412
        ],
        [
          9000,
          2.788898468017578
        ],
        [
          9500,
          2.723479747772217
        ],
        [
          10000,
          2.772564649581909
        ],
        [
          10500,
          2.776197910308838
        ],
        [
          11000,
          2.800644874572754
        ],
        [
          11500,
          2.934178590774536
        ],
        [
          12000,
          2.918450117111206
        ],
        [
          12500,
          2.9131672382354736
        ],
        [
          13000,
          2.988121271133423
        ],
        [
          13500,
          2.99784779548645
        ],
        [
          14000,
          3.009276866912842
        ],
        [
          14500,
          3.0496091842651367
        ],
        [
          15000,
          2.994673490524292
        ],
        [
          15500,
          3.0826432704925537
        ],
        [
          16000,
          3.0948662757873535
        ],
        [
          16500,
          3.115873336791992
        ],
        [
          17000,
          3.190565824508667
        ],
        [
          17500,
          3.1681480407714844
        ],
        [
          18000,
          3.147430419921875
        ],
        [
          18500,
          3.1660985946655273
        ],
        [
          19000,
          3.2304000854492188
        ],
        [
          19500,
          3.171257972717285
        ],
        [
          20000,
          3.2632808685302734
        ],
        [
          20500,
          3.2505602836608887
        ],
        [
          21000,
          3.2676539421081543
        ],
        [
          21500,
          3.2445731163024902
        ],
        [
          22000,
          3.3247578144073486
        ],
        [
          22500,
          3.2380270957946777
        ],
        [
          23000,
          3.2987163066864014
        ],
        [
          23500,
          3.3738856315612793
        ],
        [
          24000,
          3.29162335395813
        ],
        [
          24500,
          3.276959180831909
        ],
        [
          25000,
          3.278876543045044
        ],
        [
          25500,
          3.3395562171936035
        ],
        [
          26000,
          3.3200314044952393
        ],
        [
          26500,
          3.289020538330078
        ],
        [
          27000,
          3.3816592693328857
        ],
        [
          27500,
          3.3119258880615234
        ],
        [
          28000,
          3.3798892498016357
        ],
        [
          28500,
          3.3524250984191895
        ],
        [
          29000,
          3.290367603302002
        ],
        [
          29500,
          3.354862928390503
        ],
        [
          30000,
          3.3930187225341797
        ],
        [
          30500,
          3.4535584449768066
        ],
        [
          31000,
          3.40474009513855
        ],
        [
          31500,
          3.3824450969696045
        ],
        [
          32000,
          3.3416175842285156
        ],
        [
          32500,
          3.3829944133758545
        ],
        [
          33000,
          3.47367787361145
        ],
        [
          33500,
          3.38017201423645
        ],
        [
          34000,
          3.423426866531372
        ],
        [
          34500,
          3.432776689529419
        ],
        [
          35000,
          3.3909225463867188
        ],
        [
          35500,
          3.4040558338165283
        ],
        [
          36000,
          3.43444561958313
        ],
        [
          36500,
          3.4230575561523438
        ],
        [
          37000,
          3.400352954864502
        ],
        [
          37500,
          3.4209342002868652
        ],
        [
          38000,
          3.4925525188446045
        ],
        [
          38500,
          3.4681191444396973
        ],
        [
          39000,
          3.413693904876709
        ],
        [
          39500,
          3.4114742279052734
        ],
        [
          40000,
          3.4711005687713623
        ],
        [
          40500,
          3.462751865386963
        ],
        [
          41000,
          3.4486083984375
        ],
        [
          41500,
          3.5280323028564453
        ],
        [
          42000,
          3.4371237754821777
        ],
        [
          42500,
          3.4854578971862793
        ],
        [
          43000,
          3.450110673904419
        ],
        [
          43500,
          3.495943784713745
        ],
        [
          44000,
          3.414825916290283
        ],
        [
          44500,
          3.492988109588623
        ],
        [
          45000,
          3.498607635498047
        ],
        [
          45500,
          3.552642345428467
        ],
        [
          46000,
          3.512225389480591
        ],
        [
          46500,
          3.5342869758605957
        ],
        [
          47000,
          3.459961414337158
        ],
        [
          47500,
          3.531271457672119
        ],
        [
          48000,
          3.5064570903778076
        ],
        [
          48500,
          3.5012078285217285
        ],
        [
          49000,
          3.4067184925079346
        ],
        [
          49500,
          3.5370781421661377
        ],
        [
          50000,
          3.5304408073425293
        ],
        [
          50500,
          3.5088043212890625
        ],
        [
          51000,
          3.524399518966675
        ],
        [
          51500,
          3.5354247093200684
        ],
        [
          52000,
          3.5239322185516357
        ]
      ]
    },
    "5": {
      "converged": true,
      "hit_cap": false,
      "trustworthy": false,
      "still_improving_at_stop": false,
      "diverged": true,
      "stop_epoch": 11000,
      "best_val": 1.0346213579177856,
      "best_epoch": 5000,
      "recent_improvement": -0.004636526107788086,
      "trajectory": [
        [
          500,
          4.842042922973633
        ],
        [
          1000,
          4.875439643859863
        ],
        [
          1500,
          4.913824081420898
        ],
        [
          2000,
          4.114824295043945
        ],
        [
          2500,
          2.5361573696136475
        ],
        [
          3000,
          1.0699543952941895
        ],
        [
          3500,
          1.1090168952941895
        ],
        [
          4000,
          1.0610008239746094
        ],
        [
          4500,
          1.1025197505950928
        ],
        [
          5000,
          1.0346213579177856
        ],
        [
          5500,
          1.1377182006835938
        ],
        [
          6000,
          1.1856915950775146
        ],
        [
          6500,
          1.2181636095046997
        ],
        [
          7000,
          1.2688664197921753
        ],
        [
          7500,
          1.407841444015503
        ],
        [
          8000,
          1.3610296249389648
        ],
        [
          8500,
          1.4367578029632568
        ],
        [
          9000,
          1.615330696105957
        ],
        [
          9500,
          1.5325055122375488
        ],
        [
          10000,
          1.6080080270767212
        ],
        [
          10500,
          1.5893694162368774
        ],
        [
          11000,
          1.631524682044983
        ],
        [
          11500,
          1.7813276052474976
        ],
        [
          12000,
          1.8113174438476562
        ],
        [
          12500,
          1.7992931604385376
        ],
        [
          13000,
          1.8856735229492188
        ],
        [
          13500,
          1.9442821741104126
        ],
        [
          14000,
          1.94626784324646
        ],
        [
          14500,
          1.9768213033676147
        ],
        [
          15000,
          1.9979358911514282
        ],
        [
          15500,
          2.027597665786743
        ],
        [
          16000,
          2.0197126865386963
        ],
        [
          16500,
          2.0697810649871826
        ],
        [
          17000,
          2.152268409729004
        ],
        [
          17500,
          2.1499500274658203
        ],
        [
          18000,
          2.138756275177002
        ],
        [
          18500,
          2.1443612575531006
        ],
        [
          19000,
          2.181173801422119
        ],
        [
          19500,
          2.1652700901031494
        ],
        [
          20000,
          2.2729785442352295
        ],
        [
          20500,
          2.251760959625244
        ],
        [
          21000,
          2.29673433303833
        ],
        [
          21500,
          2.2405929565429688
        ],
        [
          22000,
          2.339189052581787
        ],
        [
          22500,
          2.2640669345855713
        ],
        [
          23000,
          2.3350672721862793
        ],
        [
          23500,
          2.379751205444336
        ],
        [
          24000,
          2.270629644393921
        ],
        [
          24500,
          2.3238255977630615
        ],
        [
          25000,
          2.3419342041015625
        ],
        [
          25500,
          2.375687599182129
        ],
        [
          26000,
          2.3504910469055176
        ],
        [
          26500,
          2.3691439628601074
        ],
        [
          27000,
          2.4264261722564697
        ],
        [
          27500,
          2.3988499641418457
        ],
        [
          28000,
          2.4481568336486816
        ],
        [
          28500,
          2.3708174228668213
        ],
        [
          29000,
          2.3724212646484375
        ],
        [
          29500,
          2.4561526775360107
        ],
        [
          30000,
          2.5588858127593994
        ],
        [
          30500,
          2.493962287902832
        ],
        [
          31000,
          2.500223398208618
        ],
        [
          31500,
          2.5281643867492676
        ],
        [
          32000,
          2.498014211654663
        ],
        [
          32500,
          2.4974029064178467
        ],
        [
          33000,
          2.540374994277954
        ],
        [
          33500,
          2.5062878131866455
        ],
        [
          34000,
          2.489438533782959
        ],
        [
          34500,
          2.580984115600586
        ],
        [
          35000,
          2.458231210708618
        ],
        [
          35500,
          2.52194881439209
        ],
        [
          36000,
          2.567859172821045
        ],
        [
          36500,
          2.4901506900787354
        ],
        [
          37000,
          2.5162692070007324
        ],
        [
          37500,
          2.530992031097412
        ],
        [
          38000,
          2.5950427055358887
        ],
        [
          38500,
          2.5698041915893555
        ],
        [
          39000,
          2.5678493976593018
        ],
        [
          39500,
          2.529778003692627
        ],
        [
          40000,
          2.5880141258239746
        ],
        [
          40500,
          2.5569944381713867
        ],
        [
          41000,
          2.582528591156006
        ],
        [
          41500,
          2.698249340057373
        ],
        [
          42000,
          2.537496566772461
        ],
        [
          42500,
          2.677016019821167
        ],
        [
          43000,
          2.6367738246917725
        ],
        [
          43500,
          2.602200984954834
        ],
        [
          44000,
          2.553032159805298
        ],
        [
          44500,
          2.6075966358184814
        ],
        [
          45000,
          2.6460366249084473
        ],
        [
          45500,
          2.6883091926574707
        ],
        [
          46000,
          2.6249032020568848
        ],
        [
          46500,
          2.641082525253296
        ],
        [
          47000,
          2.6067867279052734
        ],
        [
          47500,
          2.6739189624786377
        ],
        [
          48000,
          2.589148759841919
        ],
        [
          48500,
          2.5822744369506836
        ],
        [
          49000,
          2.585432291030884
        ],
        [
          49500,
          2.60172700881958
        ],
        [
          50000,
          2.6417479515075684
        ],
        [
          50500,
          2.6378514766693115
        ],
        [
          51000,
          2.636019229888916
        ],
        [
          51500,
          2.6940152645111084
        ],
        [
          52000,
          2.629539728164673
        ]
      ]
    },
    "6": {
      "converged": true,
      "hit_cap": false,
      "trustworthy": false,
      "still_improving_at_stop": true,
      "diverged": true,
      "stop_epoch": 9000,
      "best_val": 0.8886451721191406,
      "best_epoch": 3000,
      "recent_improvement": 0.017288684844970703,
      "trajectory": [
        [
          500,
          4.843020439147949
        ],
        [
          1000,
          4.849941730499268
        ],
        [
          1500,
          4.924960613250732
        ],
        [
          2000,
          3.969209671020508
        ],
        [
          2500,
          1.1192543506622314
        ],
        [
          3000,
          0.8886451721191406
        ],
        [
          3500,
          0.9078251123428345
        ],
        [
          4000,
          1.045050859451294
        ],
        [
          4500,
          1.1239303350448608
        ],
        [
          5000,
          1.125859022140503
        ],
        [
          5500,
          1.2543716430664062
        ],
        [
          6000,
          1.2840558290481567
        ],
        [
          6500,
          1.3885496854782104
        ],
        [
          7000,
          1.458195447921753
        ],
        [
          7500,
          1.6491409540176392
        ],
        [
          8000,
          1.5900464057922363
        ],
        [
          8500,
          1.6962982416152954
        ],
        [
          9000,
          1.811697006225586
        ],
        [
          9500,
          1.8536752462387085
        ],
        [
          10000,
          1.9469858407974243
        ],
        [
          10500,
          1.9496835470199585
        ],
        [
          11000,
          2.006635904312134
        ],
        [
          11500,
          2.1410858631134033
        ],
        [
          12000,
          2.244655132293701
        ],
        [
          12500,
          2.204472541809082
        ],
        [
          13000,
          2.2925710678100586
        ],
        [
          13500,
          2.358525276184082
        ],
        [
          14000,
          2.4060451984405518
        ],
        [
          14500,
          2.4207959175109863
        ],
        [
          15000,
          2.3671762943267822
        ],
        [
          15500,
          2.490198850631714
        ],
        [
          16000,
          2.5251736640930176
        ],
        [
          16500,
          2.529233932495117
        ],
        [
          17000,
          2.609717607498169
        ],
        [
          17500,
          2.6753768920898438
        ],
        [
          18000,
          2.5631184577941895
        ],
        [
          18500,
          2.619809627532959
        ],
        [
          19000,
          2.673187732696533
        ],
        [
          19500,
          2.618351936340332
        ],
        [
          20000,
          2.7321910858154297
        ],
        [
          20500,
          2.6678848266601562
        ],
        [
          21000,
          2.7979495525360107
        ],
        [
          21500,
          2.7436156272888184
        ],
        [
          22000,
          2.8552088737487793
        ],
        [
          22500,
          2.7810940742492676
        ],
        [
          23000,
          2.843963146209717
        ],
        [
          23500,
          2.8616678714752197
        ],
        [
          24000,
          2.8196189403533936
        ],
        [
          24500,
          2.8077056407928467
        ],
        [
          25000,
          2.847726345062256
        ],
        [
          25500,
          2.882704973220825
        ],
        [
          26000,
          2.8472073078155518
        ],
        [
          26500,
          2.8014073371887207
        ],
        [
          27000,
          2.952904224395752
        ],
        [
          27500,
          2.92874813079834
        ],
        [
          28000,
          2.9406497478485107
        ],
        [
          28500,
          2.8919129371643066
        ],
        [
          29000,
          2.873384714126587
        ],
        [
          29500,
          2.9536163806915283
        ],
        [
          30000,
          3.0005431175231934
        ],
        [
          30500,
          3.0027623176574707
        ],
        [
          31000,
          3.018717050552368
        ],
        [
          31500,
          3.0456511974334717
        ],
        [
          32000,
          3.0409440994262695
        ],
        [
          32500,
          3.027066707611084
        ],
        [
          33000,
          3.0424816608428955
        ],
        [
          33500,
          3.0352487564086914
        ],
        [
          34000,
          3.0662424564361572
        ],
        [
          34500,
          3.0868544578552246
        ],
        [
          35000,
          3.0049850940704346
        ],
        [
          35500,
          3.0757625102996826
        ],
        [
          36000,
          3.0998406410217285
        ],
        [
          36500,
          3.0573627948760986
        ],
        [
          37000,
          3.0376405715942383
        ],
        [
          37500,
          3.1053035259246826
        ],
        [
          38000,
          3.121492624282837
        ],
        [
          38500,
          3.1072213649749756
        ],
        [
          39000,
          3.0877957344055176
        ],
        [
          39500,
          3.077366828918457
        ],
        [
          40000,
          3.099210262298584
        ],
        [
          40500,
          3.119124174118042
        ],
        [
          41000,
          3.0921471118927
        ],
        [
          41500,
          3.332277297973633
        ],
        [
          42000,
          3.106170892715454
        ],
        [
          42500,
          3.1961402893066406
        ],
        [
          43000,
          3.190612316131592
        ],
        [
          43500,
          3.1591532230377197
        ],
        [
          44000,
          3.1518359184265137
        ],
        [
          44500,
          3.2703545093536377
        ],
        [
          45000,
          3.1771256923675537
        ],
        [
          45500,
          3.2614669799804688
        ],
        [
          46000,
          3.2910900115966797
        ],
        [
          46500,
          3.2414557933807373
        ],
        [
          47000,
          3.243302822113037
        ],
        [
          47500,
          3.3562045097351074
        ],
        [
          48000,
          3.2615838050842285
        ],
        [
          48500,
          3.229499340057373
        ],
        [
          49000,
          3.2300217151641846
        ],
        [
          49500,
          3.326791286468506
        ],
        [
          50000,
          3.2650208473205566
        ],
        [
          50500,
          3.302659273147583
        ],
        [
          51000,
          3.403759479522705
        ],
        [
          51500,
          3.3342766761779785
        ],
        [
          52000,
          3.273801326751709
        ]
      ]
    },
    "7": {
      "converged": true,
      "hit_cap": false,
      "trustworthy": false,
      "still_improving_at_stop": false,
      "diverged": true,
      "stop_epoch": 9000,
      "best_val": 0.9190894961357117,
      "best_epoch": 3000,
      "recent_improvement": -0.006270885467529297,
      "trajectory": [
        [
          500,
          4.8524088859558105
        ],
        [
          1000,
          4.8617353439331055
        ],
        [
          1500,
          4.904980659484863
        ],
        [
          2000,
          3.9751880168914795
        ],
        [
          2500,
          1.1970698833465576
        ],
        [
          3000,
          0.9190894961357117
        ],
        [
          3500,
          0.9338383674621582
        ],
        [
          4000,
          1.0511224269866943
        ],
        [
          4500,
          1.1256599426269531
        ],
        [
          5000,
          1.121058702468872
        ],
        [
          5500,
          1.238760232925415
        ],
        [
          6000,
          1.2435534000396729
        ],
        [
          6500,
          1.2882252931594849
        ],
        [
          7000,
          1.3510794639587402
        ],
        [
          7500,
          1.4967097043991089
        ],
        [
          8000,
          1.4970862865447998
        ],
        [
          8500,
          1.6033166646957397
        ],
        [
          9000,
          1.692413568496704
        ],
        [
          9500,
          1.7713502645492554
        ],
        [
          10000,
          1.8300001621246338
        ],
        [
          10500,
          1.8566510677337646
        ],
        [
          11000,
          1.9157577753067017
        ],
        [
          11500,
          2.1007239818573
        ],
        [
          12000,
          2.122683048248291
        ],
        [
          12500,
          2.167898654937744
        ],
        [
          13000,
          2.224031686782837
        ],
        [
          13500,
          2.360346555709839
        ],
        [
          14000,
          2.3873703479766846
        ],
        [
          14500,
          2.3681142330169678
        ],
        [
          15000,
          2.309295177459717
        ],
        [
          15500,
          2.456873655319214
        ],
        [
          16000,
          2.43821120262146
        ],
        [
          16500,
          2.5021958351135254
        ],
        [
          17000,
          2.524578094482422
        ],
        [
          17500,
          2.6602025032043457
        ],
        [
          18000,
          2.619868278503418
        ],
        [
          18500,
          2.6231162548065186
        ],
        [
          19000,
          2.661527395248413
        ],
        [
          19500,
          2.5928142070770264
        ],
        [
          20000,
          2.6782212257385254
        ],
        [
          20500,
          2.7188034057617188
        ],
        [
          21000,
          2.7178924083709717
        ],
        [
          21500,
          2.6961402893066406
        ],
        [
          22000,
          2.8715646266937256
        ],
        [
          22500,
          2.7350618839263916
        ],
        [
          23000,
          2.788886547088623
        ],
        [
          23500,
          2.858769416809082
        ],
        [
          24000,
          2.8170371055603027
        ],
        [
          24500,
          2.825165271759033
        ],
        [
          25000,
          2.8162598609924316
        ],
        [
          25500,
          2.8908584117889404
        ],
        [
          26000,
          2.8390815258026123
        ],
        [
          26500,
          2.8094310760498047
        ],
        [
          27000,
          2.9761195182800293
        ],
        [
          27500,
          2.9101741313934326
        ],
        [
          28000,
          2.985964298248291
        ],
        [
          28500,
          2.872983455657959
        ],
        [
          29000,
          2.911878824234009
        ],
        [
          29500,
          2.923186779022217
        ],
        [
          30000,
          2.979565382003784
        ],
        [
          30500,
          3.084062337875366
        ],
        [
          31000,
          3.048957347869873
        ],
        [
          31500,
          3.166837692260742
        ],
        [
          32000,
          2.9924747943878174
        ],
        [
          32500,
          2.9931678771972656
        ],
        [
          33000,
          3.0461812019348145
        ],
        [
          33500,
          2.9847593307495117
        ],
        [
          34000,
          3.07129168510437
        ],
        [
          34500,
          3.106074810028076
        ],
        [
          35000,
          3.0340213775634766
        ],
        [
          35500,
          3.1324410438537598
        ],
        [
          36000,
          3.1686558723449707
        ],
        [
          36500,
          3.101682424545288
        ],
        [
          37000,
          3.0640950202941895
        ],
        [
          37500,
          3.119560718536377
        ],
        [
          38000,
          3.230551242828369
        ],
        [
          38500,
          3.1278300285339355
        ],
        [
          39000,
          3.124415874481201
        ],
        [
          39500,
          3.1014938354492188
        ],
        [
          40000,
          3.1168456077575684
        ],
        [
          40500,
          3.1530022621154785
        ],
        [
          41000,
          3.168858766555786
        ],
        [
          41500,
          3.1947386264801025
        ],
        [
          42000,
          3.1651432514190674
        ],
        [
          42500,
          3.2530837059020996
        ],
        [
          43000,
          3.1937758922576904
        ],
        [
          43500,
          3.2040939331054688
        ],
        [
          44000,
          3.1623988151550293
        ],
        [
          44500,
          3.2307662963867188
        ],
        [
          45000,
          3.257392168045044
        ],
        [
          45500,
          3.1901283264160156
        ],
        [
          46000,
          3.2635955810546875
        ],
        [
          46500,
          3.2787253856658936
        ],
        [
          47000,
          3.320941925048828
        ],
        [
          47500,
          3.353346586227417
        ],
        [
          48000,
          3.2617123126983643
        ],
        [
          48500,
          3.2630298137664795
        ],
        [
          49000,
          3.2561516761779785
        ],
        [
          49500,
          3.3458969593048096
        ],
        [
          50000,
          3.2366607189178467
        ],
        [
          50500,
          3.313286542892456
        ],
        [
          51000,
          3.3673598766326904
        ],
        [
          51500,
          3.4018027782440186
        ],
        [
          52000,
          3.269866466522217
        ]
      ]
    },
    "8": {
      "converged": true,
      "hit_cap": false,
      "trustworthy": false,
      "still_improving_at_stop": true,
      "diverged": true,
      "stop_epoch": 9000,
      "best_val": 0.960760235786438,
      "best_epoch": 3000,
      "recent_improvement": 0.2289118766784668,
      "trajectory": [
        [
          500,
          4.913690567016602
        ],
        [
          1000,
          4.998450756072998
        ],
        [
          1500,
          4.974001884460449
        ],
        [
          2000,
          3.021404981613159
        ],
        [
          2500,
          1.174006700515747
        ],
        [
          3000,
          0.960760235786438
        ],
        [
          3500,
          0.9681447148323059
        ],
        [
          4000,
          1.1087175607681274
        ],
        [
          4500,
          1.110349178314209
        ],
        [
          5000,
          1.0974595546722412
        ],
        [
          5500,
          1.218109369277954
        ],
        [
          6000,
          1.2068313360214233
        ],
        [
          6500,
          1.3070367574691772
        ],
        [
          7000,
          1.4353382587432861
        ],
        [
          7500,
          1.5400530099868774
        ],
        [
          8000,
          1.4870537519454956
        ],
        [
          8500,
          1.596752405166626
        ],
        [
          9000,
          1.7721322774887085
        ],
        [
          9500,
          1.699804663658142
        ],
        [
          10000,
          1.73787522315979
        ],
        [
          10500,
          1.7260663509368896
        ],
        [
          11000,
          1.7615379095077515
        ],
        [
          11500,
          1.926661729812622
        ],
        [
          12000,
          1.9365174770355225
        ],
        [
          12500,
          1.872196912765503
        ],
        [
          13000,
          1.9619245529174805
        ],
        [
          13500,
          2.0227465629577637
        ],
        [
          14000,
          2.024906635284424
        ],
        [
          14500,
          2.0746617317199707
        ],
        [
          15000,
          2.0809338092803955
        ],
        [
          15500,
          2.1338117122650146
        ],
        [
          16000,
          2.171276807785034
        ],
        [
          16500,
          2.1733813285827637
        ],
        [
          17000,
          2.2487382888793945
        ],
        [
          17500,
          2.263397693634033
        ],
        [
          18000,
          2.3241026401519775
        ],
        [
          18500,
          2.334042549133301
        ],
        [
          19000,
          2.3936448097229004
        ],
        [
          19500,
          2.351257085800171
        ],
        [
          20000,
          2.4019179344177246
        ],
        [
          20500,
          2.4359471797943115
        ],
        [
          21000,
          2.4363932609558105
        ],
        [
          21500,
          2.5005922317504883
        ],
        [
          22000,
          2.5963973999023438
        ],
        [
          22500,
          2.500030517578125
        ],
        [
          23000,
          2.538532018661499
        ],
        [
          23500,
          2.621324300765991
        ],
        [
          24000,
          2.585479259490967
        ],
        [
          24500,
          2.5415875911712646
        ],
        [
          25000,
          2.5724127292633057
        ],
        [
          25500,
          2.64046049118042
        ],
        [
          26000,
          2.6178107261657715
        ],
        [
          26500,
          2.5483763217926025
        ],
        [
          27000,
          2.6660103797912598
        ],
        [
          27500,
          2.6704273223876953
        ],
        [
          28000,
          2.7365736961364746
        ],
        [
          28500,
          2.7033753395080566
        ],
        [
          29000,
          2.6767630577087402
        ],
        [
          29500,
          2.673489809036255
        ],
        [
          30000,
          2.7672171592712402
        ],
        [
          30500,
          2.765270471572876
        ],
        [
          31000,
          2.791874408721924
        ],
        [
          31500,
          2.846856117248535
        ],
        [
          32000,
          2.7995505332946777
        ],
        [
          32500,
          2.7554502487182617
        ],
        [
          33000,
          2.7655088901519775
        ],
        [
          33500,
          2.7575252056121826
        ],
        [
          34000,
          2.750619888305664
        ],
        [
          34500,
          2.7072620391845703
        ],
        [
          35000,
          2.749441623687744
        ],
        [
          35500,
          2.7582006454467773
        ],
        [
          36000,
          2.818629741668701
        ],
        [
          36500,
          2.731375217437744
        ],
        [
          37000,
          2.7329440116882324
        ],
        [
          37500,
          2.7705512046813965
        ],
        [
          38000,
          2.794640064239502
        ],
        [
          38500,
          2.7400615215301514
        ],
        [
          39000,
          2.787026882171631
        ],
        [
          39500,
          2.709219217300415
        ],
        [
          40000,
          2.7447049617767334
        ],
        [
          40500,
          2.7229740619659424
        ],
        [
          41000,
          2.6637322902679443
        ],
        [
          41500,
          2.7830069065093994
        ],
        [
          42000,
          2.723541021347046
        ],
        [
          42500,
          2.76444935798645
        ],
        [
          43000,
          2.752145767211914
        ],
        [
          43500,
          2.651005268096924
        ],
        [
          44000,
          2.6802268028259277
        ],
        [
          44500,
          2.7617850303649902
        ],
        [
          45000,
          2.712965488433838
        ],
        [
          45500,
          2.653838634490967
        ],
        [
          46000,
          2.6880452632904053
        ],
        [
          46500,
          2.630255699157715
        ],
        [
          47000,
          2.654151439666748
        ],
        [
          47500,
          2.664933681488037
        ],
        [
          48000,
          2.6206369400024414
        ],
        [
          48500,
          2.5484349727630615
        ],
        [
          49000,
          2.4856698513031006
        ],
        [
          49500,
          2.4535574913024902
        ],
        [
          50000,
          2.5073065757751465
        ],
        [
          50500,
          2.4447877407073975
        ],
        [
          51000,
          2.637510061264038
        ],
        [
          51500,
          2.6144793033599854
        ],
        [
          52000,
          2.4591333866119385
        ]
      ]
    },
    "9": {
      "converged": true,
      "hit_cap": false,
      "trustworthy": false,
      "still_improving_at_stop": true,
      "diverged": true,
      "stop_epoch": 9000,
      "best_val": 1.0786492824554443,
      "best_epoch": 3000,
      "recent_improvement": 0.28217196464538574,
      "trajectory": [
        [
          500,
          4.8976030349731445
        ],
        [
          1000,
          5.009633541107178
        ],
        [
          1500,
          5.064988136291504
        ],
        [
          2000,
          2.651571273803711
        ],
        [
          2500,
          1.1339820623397827
        ],
        [
          3000,
          1.0786492824554443
        ],
        [
          3500,
          1.1829802989959717
        ],
        [
          4000,
          1.304136037826538
        ],
        [
          4500,
          1.3344088792800903
        ],
        [
          5000,
          1.2623292207717896
        ],
        [
          5500,
          1.327725887298584
        ],
        [
          6000,
          1.3056858777999878
        ],
        [
          6500,
          1.399963617324829
        ],
        [
          7000,
          1.5244923830032349
        ],
        [
          7500,
          1.707068681716919
        ],
        [
          8000,
          1.6689523458480835
        ],
        [
          8500,
          1.8393545150756836
        ],
        [
          9000,
          1.9990863800048828
        ],
        [
          9500,
          2.0380635261535645
        ],
        [
          10000,
          2.074018955230713
        ],
        [
          10500,
          2.115480661392212
        ],
        [
          11000,
          2.187079906463623
        ],
        [
          11500,
          2.4039502143859863
        ],
        [
          12000,
          2.3923215866088867
        ],
        [
          12500,
          2.4339072704315186
        ],
        [
          13000,
          2.5535128116607666
        ],
        [
          13500,
          2.5920352935791016
        ],
        [
          14000,
          2.6415529251098633
        ],
        [
          14500,
          2.62998628616333
        ],
        [
          15000,
          2.5890707969665527
        ],
        [
          15500,
          2.725573778152466
        ],
        [
          16000,
          2.814443588256836
        ],
        [
          16500,
          2.866201639175415
        ],
        [
          17000,
          2.9244773387908936
        ],
        [
          17500,
          2.9195897579193115
        ],
        [
          18000,
          2.9067158699035645
        ],
        [
          18500,
          2.958648204803467
        ],
        [
          19000,
          3.027709484100342
        ],
        [
          19500,
          2.981938600540161
        ],
        [
          20000,
          3.101968765258789
        ],
        [
          20500,
          3.046430826187134
        ],
        [
          21000,
          3.1655778884887695
        ],
        [
          21500,
          3.1481683254241943
        ],
        [
          22000,
          3.2917721271514893
        ],
        [
          22500,
          3.132347583770752
        ],
        [
          23000,
          3.2471134662628174
        ],
        [
          23500,
          3.2723605632781982
        ],
        [
          24000,
          3.275888442993164
        ],
        [
          24500,
          3.220264434814453
        ],
        [
          25000,
          3.35203218460083
        ],
        [
          25500,
          3.4221389293670654
        ],
        [
          26000,
          3.309028148651123
        ],
        [
          26500,
          3.3051021099090576
        ],
        [
          27000,
          3.3672213554382324
        ],
        [
          27500,
          3.3816237449645996
        ],
        [
          28000,
          3.4043495655059814
        ],
        [
          28500,
          3.421687602996826
        ],
        [
          29000,
          3.374216079711914
        ],
        [
          29500,
          3.442876100540161
        ],
        [
          30000,
          3.508235216140747
        ],
        [
          30500,
          3.5738003253936768
        ],
        [
          31000,
          3.5416367053985596
        ],
        [
          31500,
          3.681442975997925
        ],
        [
          32000,
          3.5440738201141357
        ],
        [
          32500,
          3.4997589588165283
        ],
        [
          33000,
          3.5881247520446777
        ],
        [
          33500,
          3.531947374343872
        ],
        [
          34000,
          3.574596405029297
        ],
        [
          34500,
          3.652639865875244
        ],
        [
          35000,
          3.4932332038879395
        ],
        [
          35500,
          3.602586030960083
        ],
        [
          36000,
          3.6428229808807373
        ],
        [
          36500,
          3.5806002616882324
        ],
        [
          37000,
          3.5836288928985596
        ],
        [
          37500,
          3.6613917350769043
        ],
        [
          38000,
          3.639519214630127
        ],
        [
          38500,
          3.5896155834198
        ],
        [
          39000,
          3.614276170730591
        ],
        [
          39500,
          3.5290889739990234
        ],
        [
          40000,
          3.6592178344726562
        ],
        [
          40500,
          3.5551936626434326
        ],
        [
          41000,
          3.5859031677246094
        ],
        [
          41500,
          3.70473051071167
        ],
        [
          42000,
          3.611518383026123
        ],
        [
          42500,
          3.6548075675964355
        ],
        [
          43000,
          3.61664080619812
        ],
        [
          43500,
          3.5666236877441406
        ],
        [
          44000,
          3.594575881958008
        ],
        [
          44500,
          3.613510847091675
        ],
        [
          45000,
          3.514558792114258
        ],
        [
          45500,
          3.4954440593719482
        ],
        [
          46000,
          3.577638626098633
        ],
        [
          46500,
          3.5697455406188965
        ],
        [
          47000,
          3.5115840435028076
        ],
        [
          47500,
          3.484753370285034
        ],
        [
          48000,
          3.506134033203125
        ],
        [
          48500,
          3.441169023513794
        ],
        [
          49000,
          3.4246013164520264
        ],
        [
          49500,
          3.5001938343048096
        ],
        [
          50000,
          3.4029247760772705
        ],
        [
          50500,
          3.3427023887634277
        ],
        [
          51000,
          3.3540172576904297
        ],
        [
          51500,
          3.4266536235809326
        ],
        [
          52000,
          3.295466661453247
        ]
      ]
    },
    "10": {
      "converged": true,
      "hit_cap": false,
      "trustworthy": false,
      "still_improving_at_stop": true,
      "diverged": true,
      "stop_epoch": 9000,
      "best_val": 1.0981528759002686,
      "best_epoch": 3000,
      "recent_improvement": 0.32147979736328125,
      "trajectory": [
        [
          500,
          4.893056869506836
        ],
        [
          1000,
          4.9755659103393555
        ],
        [
          1500,
          5.064145565032959
        ],
        [
          2000,
          2.6809377670288086
        ],
        [
          2500,
          1.1893761157989502
        ],
        [
          3000,
          1.0981528759002686
        ],
        [
          3500,
          1.0997912883758545
        ],
        [
          4000,
          1.2662937641143799
        ],
        [
          4500,
          1.2997384071350098
        ],
        [
          5000,
          1.2394570112228394
        ],
        [
          5500,
          1.3359686136245728
        ],
        [
          6000,
          1.3156821727752686
        ],
        [
          6500,
          1.419398546218872
        ],
        [
          7000,
          1.518187403678894
        ],
        [
          7500,
          1.7319380044937134
        ],
        [
          8000,
          1.7170016765594482
        ],
        [
          8500,
          1.8880723714828491
        ],
        [
          9000,
          2.0127792358398438
        ],
        [
          9500,
          2.1111438274383545
        ],
        [
          10000,
          2.1129608154296875
        ],
        [
          10500,
          2.1743507385253906
        ],
        [
          11000,
          2.227630138397217
        ],
        [
          11500,
          2.3853139877319336
        ],
        [
          12000,
          2.441413640975952
        ],
        [
          12500,
          2.4859566688537598
        ],
        [
          13000,
          2.5314981937408447
        ],
        [
          13500,
          2.6281166076660156
        ],
        [
          14000,
          2.6812050342559814
        ],
        [
          14500,
          2.6801505088806152
        ],
        [
          15000,
          2.6205220222473145
        ],
        [
          15500,
          2.7732930183410645
        ],
        [
          16000,
          2.8300464153289795
        ],
        [
          16500,
          2.8585386276245117
        ],
        [
          17000,
          2.9319233894348145
        ],
        [
          17500,
          2.9021687507629395
        ],
        [
          18000,
          2.9966812133789062
        ],
        [
          18500,
          2.9200217723846436
        ],
        [
          19000,
          2.9828639030456543
        ],
        [
          19500,
          2.9697656631469727
        ],
        [
          20000,
          3.1664657592773438
        ],
        [
          20500,
          3.059802770614624
        ],
        [
          21000,
          3.207669734954834
        ],
        [
          21500,
          3.1567506790161133
        ],
        [
          22000,
          3.2625484466552734
        ],
        [
          22500,
          3.1762993335723877
        ],
        [
          23000,
          3.18641996383667
        ],
        [
          23500,
          3.3052666187286377
        ],
        [
          24000,
          3.2470390796661377
        ],
        [
          24500,
          3.273869037628174
        ],
        [
          25000,
          3.2883529663085938
        ],
        [
          25500,
          3.4054274559020996
        ],
        [
          26000,
          3.293397903442383
        ],
        [
          26500,
          3.3069558143615723
        ],
        [
          27000,
          3.422860622406006
        ],
        [
          27500,
          3.420010805130005
        ],
        [
          28000,
          3.4096038341522217
        ],
        [
          28500,
          3.428845167160034
        ],
        [
          29000,
          3.4118220806121826
        ],
        [
          29500,
          3.4820430278778076
        ],
        [
          30000,
          3.4841504096984863
        ],
        [
          30500,
          3.548734188079834
        ],
        [
          31000,
          3.485105037689209
        ],
        [
          31500,
          3.5578980445861816
        ],
        [
          32000,
          3.5163447856903076
        ],
        [
          32500,
          3.5366873741149902
        ],
        [
          33000,
          3.6056151390075684
        ],
        [
          33500,
          3.517571210861206
        ],
        [
          34000,
          3.554494857788086
        ],
        [
          34500,
          3.5796799659729004
        ],
        [
          35000,
          3.4762585163116455
        ],
        [
          35500,
          3.579688549041748
        ],
        [
          36000,
          3.604630708694458
        ],
        [
          36500,
          3.5289816856384277
        ],
        [
          37000,
          3.565462827682495
        ],
        [
          37500,
          3.5932374000549316
        ],
        [
          38000,
          3.623966932296753
        ],
        [
          38500,
          3.5536160469055176
        ],
        [
          39000,
          3.589141845703125
        ],
        [
          39500,
          3.499354839324951
        ],
        [
          40000,
          3.6185450553894043
        ],
        [
          40500,
          3.597796678543091
        ],
        [
          41000,
          3.5555737018585205
        ],
        [
          41500,
          3.60626220703125
        ],
        [
          42000,
          3.594820737838745
        ],
        [
          42500,
          3.653285503387451
        ],
        [
          43000,
          3.5960617065429688
        ],
        [
          43500,
          3.57938814163208
        ],
        [
          44000,
          3.5568222999572754
        ],
        [
          44500,
          3.671665906906128
        ],
        [
          45000,
          3.4831645488739014
        ],
        [
          45500,
          3.5325005054473877
        ],
        [
          46000,
          3.5645720958709717
        ],
        [
          46500,
          3.5426807403564453
        ],
        [
          47000,
          3.565549850463867
        ],
        [
          47500,
          3.6167349815368652
        ],
        [
          48000,
          3.5087742805480957
        ],
        [
          48500,
          3.4678192138671875
        ],
        [
          49000,
          3.489062786102295
        ],
        [
          49500,
          3.4284896850585938
        ],
        [
          50000,
          3.3994274139404297
        ],
        [
          50500,
          3.3795580863952637
        ],
        [
          51000,
          3.4225616455078125
        ],
        [
          51500,
          3.4069976806640625
        ],
        [
          52000,
          3.2430922985076904
        ]
      ]
    },
    "11": {
      "converged": true,
      "hit_cap": false,
      "trustworthy": false,
      "still_improving_at_stop": true,
      "diverged": true,
      "stop_epoch": 8500,
      "best_val": 0.9803163409233093,
      "best_epoch": 2500,
      "recent_improvement": 0.22963571548461914,
      "trajectory": [
        [
          500,
          4.892012596130371
        ],
        [
          1000,
          4.944912910461426
        ],
        [
          1500,
          4.95126485824585
        ],
        [
          2000,
          1.9909372329711914
        ],
        [
          2500,
          0.9803163409233093
        ],
        [
          3000,
          0.9912368059158325
        ],
        [
          3500,
          1.09009850025177
        ],
        [
          4000,
          1.2213631868362427
        ],
        [
          4500,
          1.283265471458435
        ],
        [
          5000,
          1.2001464366912842
        ],
        [
          5500,
          1.274278998374939
        ],
        [
          6000,
          1.2780482769012451
        ],
        [
          6500,
          1.3433703184127808
        ],
        [
          7000,
          1.4198378324508667
        ],
        [
          7500,
          1.564213752746582
        ],
        [
          8000,
          1.4631216526031494
        ],
        [
          8500,
          1.6524810791015625
        ],
        [
          9000,
          1.7760345935821533
        ],
        [
          9500,
          1.7648032903671265
        ],
        [
          10000,
          1.8072364330291748
        ],
        [
          10500,
          1.7917730808258057
        ],
        [
          11000,
          1.8351119756698608
        ],
        [
          11500,
          2.026331901550293
        ],
        [
          12000,
          2.0091817378997803
        ],
        [
          12500,
          2.058851957321167
        ],
        [
          13000,
          2.089520215988159
        ],
        [
          13500,
          2.2564005851745605
        ],
        [
          14000,
          2.2161126136779785
        ],
        [
          14500,
          2.276637077331543
        ],
        [
          15000,
          2.2585089206695557
        ],
        [
          15500,
          2.365293025970459
        ],
        [
          16000,
          2.49937105178833
        ],
        [
          16500,
          2.528003215789795
        ],
        [
          17000,
          2.5633811950683594
        ],
        [
          17500,
          2.499289035797119
        ],
        [
          18000,
          2.589301347732544
        ],
        [
          18500,
          2.617863178253174
        ],
        [
          19000,
          2.6412956714630127
        ],
        [
          19500,
          2.6245181560516357
        ],
        [
          20000,
          2.7395477294921875
        ],
        [
          20500,
          2.746346950531006
        ],
        [
          21000,
          2.810659885406494
        ],
        [
          21500,
          2.763758897781372
        ],
        [
          22000,
          2.8561062812805176
        ],
        [
          22500,
          2.883166790008545
        ],
        [
          23000,
          2.847017765045166
        ],
        [
          23500,
          2.9235548973083496
        ],
        [
          24000,
          2.8842360973358154
        ],
        [
          24500,
          2.8523550033569336
        ],
        [
          25000,
          2.9603021144866943
        ],
        [
          25500,
          3.049741506576538
        ],
        [
          26000,
          2.8932394981384277
        ],
        [
          26500,
          2.859456777572632
        ],
        [
          27000,
          2.981567859649658
        ],
        [
          27500,
          2.9744861125946045
        ],
        [
          28000,
          3.043767213821411
        ],
        [
          28500,
          2.874748706817627
        ],
        [
          29000,
          2.9264230728149414
        ],
        [
          29500,
          2.97894549369812
        ],
        [
          30000,
          3.0878756046295166
        ],
        [
          30500,
          3.088383913040161
        ],
        [
          31000,
          3.0871684551239014
        ],
        [
          31500,
          3.1241519451141357
        ],
        [
          32000,
          3.0770087242126465
        ],
        [
          32500,
          3.0445847511291504
        ],
        [
          33000,
          3.07116961479187
        ],
        [
          33500,
          3.0686826705932617
        ],
        [
          34000,
          3.1029253005981445
        ],
        [
          34500,
          3.161694049835205
        ],
        [
          35000,
          3.018751621246338
        ],
        [
          35500,
          3.1896719932556152
        ],
        [
          36000,
          3.123831272125244
        ],
        [
          36500,
          3.0457229614257812
        ],
        [
          37000,
          3.103092670440674
        ],
        [
          37500,
          3.1901190280914307
        ],
        [
          38000,
          3.1643590927124023
        ],
        [
          38500,
          3.1119322776794434
        ],
        [
          39000,
          3.059169292449951
        ],
        [
          39500,
          3.0978360176086426
        ],
        [
          40000,
          3.051821231842041
        ],
        [
          40500,
          3.101864814758301
        ],
        [
          41000,
          3.0888609886169434
        ],
        [
          41500,
          3.0728628635406494
        ],
        [
          42000,
          3.072688341140747
        ],
        [
          42500,
          3.0967626571655273
        ],
        [
          43000,
          3.0979416370391846
        ],
        [
          43500,
          2.9967846870422363
        ],
        [
          44000,
          2.9804439544677734
        ],
        [
          44500,
          3.0259666442871094
        ],
        [
          45000,
          3.088390588760376
        ],
        [
          45500,
          3.0585055351257324
        ],
        [
          46000,
          3.0228328704833984
        ],
        [
          46500,
          2.973741292953491
        ],
        [
          47000,
          3.0035881996154785
        ],
        [
          47500,
          3.003873586654663
        ],
        [
          48000,
          2.961172580718994
        ],
        [
          48500,
          2.9358787536621094
        ],
        [
          49000,
          2.9215781688690186
        ],
        [
          49500,
          2.983208417892456
        ],
        [
          50000,
          2.894998788833618
        ],
        [
          50500,
          2.8840150833129883
        ],
        [
          51000,
          2.9307894706726074
        ],
        [
          51500,
          2.904651165008545
        ],
        [
          52000,
          2.7931971549987793
        ]
      ]
    },
    "12": {
      "converged": true,
      "hit_cap": false,
      "trustworthy": false,
      "still_improving_at_stop": false,
      "diverged": true,
      "stop_epoch": 9000,
      "best_val": 0.9064895510673523,
      "best_epoch": 3000,
      "recent_improvement": 0.0019483566284179688,
      "trajectory": [
        [
          500,
          4.9519758224487305
        ],
        [
          1000,
          5.0316362380981445
        ],
        [
          1500,
          5.2255778312683105
        ],
        [
          2000,
          1.0946680307388306
        ],
        [
          2500,
          0.9661229848861694
        ],
        [
          3000,
          0.9064895510673523
        ],
        [
          3500,
          1.0422847270965576
        ],
        [
          4000,
          1.1538671255111694
        ],
        [
          4500,
          1.267979621887207
        ],
        [
          5000,
          1.2661455869674683
        ],
        [
          5500,
          1.3330044746398926
        ],
        [
          6000,
          1.3990914821624756
        ],
        [
          6500,
          1.4319913387298584
        ],
        [
          7000,
          1.5047767162322998
        ],
        [
          7500,
          1.6122589111328125
        ],
        [
          8000,
          1.566435694694519
        ],
        [
          8500,
          1.6851623058319092
        ],
        [
          9000,
          1.80177903175354
        ],
        [
          9500,
          1.7519162893295288
        ],
        [
          10000,
          1.794675588607788
        ],
        [
          10500,
          1.7477267980575562
        ],
        [
          11000,
          1.7990728616714478
        ],
        [
          11500,
          1.9266483783721924
        ],
        [
          12000,
          1.9112024307250977
        ],
        [
          12500,
          1.8936233520507812
        ],
        [
          13000,
          1.9997247457504272
        ],
        [
          13500,
          2.078601360321045
        ],
        [
          14000,
          2.1429390907287598
        ],
        [
          14500,
          2.09128999710083
        ],
        [
          15000,
          2.097785234451294
        ],
        [
          15500,
          2.1124446392059326
        ],
        [
          16000,
          2.2690138816833496
        ],
        [
          16500,
          2.169534206390381
        ],
        [
          17000,
          2.2525675296783447
        ],
        [
          17500,
          2.282931327819824
        ],
        [
          18000,
          2.324669361114502
        ],
        [
          18500,
          2.3274636268615723
        ],
        [
          19000,
          2.4239327907562256
        ],
        [
          19500,
          2.3731024265289307
        ],
        [
          20000,
          2.404642105102539
        ],
        [
          20500,
          2.4505555629730225
        ],
        [
          21000,
          2.5252840518951416
        ],
        [
          21500,
          2.4971585273742676
        ],
        [
          22000,
          2.5706167221069336
        ],
        [
          22500,
          2.489837646484375
        ],
        [
          23000,
          2.6077144145965576
        ],
        [
          23500,
          2.6263809204101562
        ],
        [
          24000,
          2.6373088359832764
        ],
        [
          24500,
          2.509871006011963
        ],
        [
          25000,
          2.5997278690338135
        ],
        [
          25500,
          2.5913219451904297
        ],
        [
          26000,
          2.629089593887329
        ],
        [
          26500,
          2.72160005569458
        ],
        [
          27000,
          2.6833605766296387
        ],
        [
          27500,
          2.6704416275024414
        ],
        [
          28000,
          2.8201181888580322
        ],
        [
          28500,
          2.738828182220459
        ],
        [
          29000,
          2.678638219833374
        ],
        [
          29500,
          2.8429102897644043
        ],
        [
          30000,
          2.6832478046417236
        ],
        [
          30500,
          2.769479990005493
        ],
        [
          31000,
          2.7514920234680176
        ],
        [
          31500,
          2.782975673675537
        ],
        [
          32000,
          2.792208433151245
        ],
        [
          32500,
          2.7647595405578613
        ],
        [
          33000,
          2.756284475326538
        ],
        [
          33500,
          2.782191753387451
        ],
        [
          34000,
          2.8145861625671387
        ],
        [
          34500,
          2.765260696411133
        ],
        [
          35000,
          2.8024978637695312
        ],
        [
          35500,
          2.7960731983184814
        ],
        [
          36000,
          2.8802943229675293
        ],
        [
          36500,
          2.861624240875244
        ],
        [
          37000,
          2.8386189937591553
        ],
        [
          37500,
          2.8605308532714844
        ],
        [
          38000,
          2.87695050239563
        ],
        [
          38500,
          2.959861993789673
        ],
        [
          39000,
          2.852771043777466
        ],
        [
          39500,
          2.935993194580078
        ],
        [
          40000,
          2.828575611114502
        ],
        [
          40500,
          2.9132025241851807
        ],
        [
          41000,
          2.8378520011901855
        ],
        [
          41500,
          2.849231243133545
        ],
        [
          42000,
          2.946585178375244
        ],
        [
          42500,
          3.0390820503234863
        ],
        [
          43000,
          2.9262402057647705
        ],
        [
          43500,
          2.851593494415283
        ],
        [
          44000,
          2.82194185256958
        ],
        [
          44500,
          2.803525447845459
        ],
        [
          45000,
          2.974882125854492
        ],
        [
          45500,
          2.878983974456787
        ],
        [
          46000,
          2.8626580238342285
        ],
        [
          46500,
          2.8838682174682617
        ],
        [
          47000,
          3.0312256813049316
        ],
        [
          47500,
          2.817307233810425
        ],
        [
          48000,
          2.918398141860962
        ],
        [
          48500,
          2.811307907104492
        ],
        [
          49000,
          2.8549609184265137
        ],
        [
          49500,
          2.8956170082092285
        ],
        [
          50000,
          2.8863320350646973
        ],
        [
          50500,
          2.928290843963623
        ],
        [
          51000,
          2.980893611907959
        ],
        [
          51500,
          2.921884298324585
        ],
        [
          52000,
          2.8607096672058105
        ]
      ]
    }
  },
  "n_widths_trustworthy": 3,
  "all_widths_trustworthy": false,
  "hit_cap": false,
  "train_wall_clock_s": 77.33053642394952,
  "steps_to_converge": 52000,
  "train_mse_by_width": {
    "1": 0.6797820329666138,
    "2": 0.6635094285011292,
    "3": 0.6542934775352478,
    "4": 0.4267311096191406,
    "5": 0.23539812862873077,
    "6": 0.19133612513542175,
    "7": 0.19168731570243835,
    "8": 0.19353525340557098,
    "9": 0.17777377367019653,
    "10": 0.16796550154685974,
    "11": 0.17203649878501892,
    "12": 0.149481862783432
  },
  "held_out_mse_by_width": {
    "1": 1.0095927715301514,
    "2": 0.9825116991996765,
    "3": 0.9643017053604126,
    "4": 0.48146820068359375,
    "5": 0.21316829323768616,
    "6": 0.1770458221435547,
    "7": 0.1831112802028656,
    "8": 0.19141340255737305,
    "9": 0.21490056812763214,
    "10": 0.21878628432750702,
    "11": 0.1974852830171585,
    "12": 0.18060097098350525
  },
  "full_width_held_out_mse": 0.18060097098350525,
  "train_minus_heldout_gap_by_width": {
    "1": -0.3298107385635376,
    "2": -0.31900227069854736,
    "3": -0.3100082278251648,
    "4": -0.054737091064453125,
    "5": 0.022229835391044617,
    "6": 0.014290302991867065,
    "7": 0.008576035499572754,
    "8": 0.002121850848197937,
    "9": -0.03712679445743561,
    "10": -0.05082078278064728,
    "11": -0.025448784232139587,
    "12": -0.031119108200073242
  },
  "params_allocated": 180,
  "params_effective": 78,
  "executed_flops_by_width": {
    "1": 2,
    "2": 4,
    "3": 6,
    "4": 8,
    "5": 10,
    "6": 12,
    "7": 14,
    "8": 16,
    "9": 18,
    "10": 20,
    "11": 22,
    "12": 24
  },
  "fit_bar": {
    "m_hard_wmax": 0.027226459254645383,
    "floor_hard": 0.0225,
    "ratio_to_floor": 1.210064855762017,
    "pass": true,
    "strong_pass": false
  },
  "ordering_statistic": {
    "baseline_report_mse": 0.1967279314994812,
    "importance_by_unit": {
      "1": 0.10397610068321228,
      "2": 0.9523295760154724,
      "3": 0.1421864926815033,
      "4": 1.811733067035675,
      "5": 5.824052155017853,
      "6": 0.02507460117340088,
      "7": 0.14665234088897705,
      "8": 2.201846659183502,
      "9": 1.4454415440559387,
      "10": 9.53455239534378,
      "11": 16.26711255311966,
      "12": 0.25654399394989014
    },
    "spearman_index_vs_importance": {
      "rho": 0.4825174825174825,
      "p": 0.11210929146889187
    },
    "prefix_report_mse_by_k": {
      "1": 0.7742701380404001,
      "2": 0.6983839883048996,
      "3": 0.6904891483999515,
      "4": 0.6121567265787472,
      "5": 0.3263577816639233,
      "6": 0.24587315734099194,
      "7": 0.1971103521739427,
      "8": 0.20884363393751101,
      "9": 0.20616159752329707,
      "10": 0.20451943578953538,
      "11": 0.18201487389372495,
      "12": 0.1876935699151042
    },
    "greedy_report_mse_by_k": {
      "1": 0.7742701380404001,
      "2": 0.6571533744117594,
      "3": 0.5309103276072838,
      "4": 0.33407320130396245,
      "5": 0.2576604319293571,
      "6": 0.19633488027322396,
      "7": 0.19842040529475938,
      "8": 0.19279742208666958,
      "9": 0.19019124236204965,
      "10": 0.1846080367112322,
      "11": 0.18555648932845115,
      "12": 0.18769356991510525
    },
    "greedy_order_0indexed": [
      0,
      5,
      7,
      4,
      3,
      6,
      10,
      1,
      11,
      9,
      8,
      2
    ],
    "mean_relative_prefix_gap": 0.16366851231672183
  },
  "selected_width_global": {
    "selected_width": 12,
    "held_out_curve_by_width": {
      "1": 0.813512921333313,
      "2": 0.7564719319343567,
      "3": 0.747369647026062,
      "4": 0.6155490875244141,
      "5": 0.35591211915016174,
      "6": 0.3104265034198761,
      "7": 0.3132795989513397,
      "8": 0.31716224551200867,
      "9": 0.29845231771469116,
      "10": 0.2806490361690521,
      "11": 0.27619779109954834,
      "12": 0.22505702078342438
    }
  },
  "selected_width_distilled_router": {
    "tolerance": 0.25,
    "mean_selected_width": 5.269461077844311,
    "width_counts": {
      "1": 59,
      "2": 1,
      "3": 8,
      "4": 6,
      "5": 36,
      "6": 6,
      "7": 9,
      "8": 0,
      "9": 0,
      "10": 6,
      "11": 0,
      "12": 36
    }
  },
  "training_schedule": "sandwich",
  "cascade_extra_readout_bias_freedom": false,
  "provenance": {
    "timestamp_utc": "2026-07-22T17:46:33+00:00",
    "git": {
      "commit": "6f36a3e0798cc5407e58d862495532c6e3ccd48f",
      "dirty": true
    },
    "python": "3.12.13",
    "torch": "2.10.0+xpu",
    "numpy": "2.4.3",
    "platform": "Linux-7.1.3-200.fc44.x86_64-x86_64-with-glibc2.43",
    "threads": {
      "omp_num_threads": "4",
      "torch_num_threads": 4,
      "cpu_count": 22
    },
    "automl_device": "cpu"
  }
}