{
  "arm": "b",
  "seed": 2,
  "toy": "hetero",
  "n_train": 1500,
  "n_test": 500,
  "sigma": 0.05,
  "w_max": 12,
  "convergence": {
    "1": {
      "converged": true,
      "hit_cap": false,
      "trustworthy": true,
      "still_improving_at_stop": false,
      "diverged": false,
      "stop_epoch": 9500,
      "best_val": 0.8367014527320862,
      "best_epoch": 3500,
      "recent_improvement": 0.00016069412231445312,
      "trajectory": [
        [
          500,
          0.839734673500061
        ],
        [
          1000,
          0.8392210602760315
        ],
        [
          1500,
          0.8443692922592163
        ],
        [
          2000,
          0.842319905757904
        ],
        [
          2500,
          0.8392878174781799
        ],
        [
          3000,
          0.8379733562469482
        ],
        [
          3500,
          0.8367014527320862
        ],
        [
          4000,
          0.8368542194366455
        ],
        [
          4500,
          0.8375752568244934
        ],
        [
          5000,
          0.8367310762405396
        ],
        [
          5500,
          0.8394250273704529
        ],
        [
          6000,
          0.8401168584823608
        ],
        [
          6500,
          0.8354697823524475
        ],
        [
          7000,
          0.8426274657249451
        ],
        [
          7500,
          0.8415932655334473
        ],
        [
          8000,
          0.841118335723877
        ],
        [
          8500,
          0.8400682806968689
        ],
        [
          9000,
          0.841764509677887
        ],
        [
          9500,
          0.8413611054420471
        ],
        [
          10000,
          0.8412920236587524
        ],
        [
          10500,
          0.8413769602775574
        ],
        [
          11000,
          0.840969443321228
        ],
        [
          11500,
          0.8415825366973877
        ],
        [
          12000,
          0.8415822386741638
        ],
        [
          12500,
          0.8415418863296509
        ],
        [
          13000,
          0.8418567776679993
        ],
        [
          13500,
          0.8413249850273132
        ],
        [
          14000,
          0.8415917754173279
        ],
        [
          14500,
          0.8415220379829407
        ],
        [
          15000,
          0.8419303894042969
        ],
        [
          15500,
          0.8413756489753723
        ],
        [
          16000,
          0.8417515754699707
        ],
        [
          16500,
          0.841498076915741
        ],
        [
          17000,
          0.8414483666419983
        ],
        [
          17500,
          0.8431127667427063
        ],
        [
          18000,
          0.8414099216461182
        ],
        [
          18500,
          0.8414521813392639
        ],
        [
          19000,
          0.8417369723320007
        ],
        [
          19500,
          0.8415877223014832
        ],
        [
          20000,
          0.841569721698761
        ],
        [
          20500,
          0.8415601849555969
        ],
        [
          21000,
          0.8414835929870605
        ],
        [
          21500,
          0.8413019776344299
        ],
        [
          22000,
          0.8415547609329224
        ],
        [
          22500,
          0.841658353805542
        ],
        [
          23000,
          0.8415198922157288
        ],
        [
          23500,
          0.8411585688591003
        ],
        [
          24000,
          0.8415446877479553
        ],
        [
          24500,
          0.842073380947113
        ],
        [
          25000,
          0.84173583984375
        ],
        [
          25500,
          0.8415694236755371
        ],
        [
          26000,
          0.8415263295173645
        ],
        [
          26500,
          0.8414595723152161
        ],
        [
          27000,
          0.8415811061859131
        ],
        [
          27500,
          0.8415188789367676
        ],
        [
          28000,
          0.8414948582649231
        ],
        [
          28500,
          0.841492235660553
        ],
        [
          29000,
          0.8413495421409607
        ],
        [
          29500,
          0.8413907885551453
        ],
        [
          30000,
          0.841614305973053
        ],
        [
          30500,
          0.8407990336418152
        ],
        [
          31000,
          0.8416463136672974
        ],
        [
          31500,
          0.8414885401725769
        ],
        [
          32000,
          0.8415772318840027
        ],
        [
          32500,
          0.8408458828926086
        ],
        [
          33000,
          0.8414204120635986
        ]
      ]
    },
    "2": {
      "converged": true,
      "hit_cap": false,
      "trustworthy": true,
      "still_improving_at_stop": false,
      "diverged": false,
      "stop_epoch": 8000,
      "best_val": 0.5860008597373962,
      "best_epoch": 2000,
      "recent_improvement": -0.0006578564643859863,
      "trajectory": [
        [
          500,
          0.682428777217865
        ],
        [
          1000,
          0.6332967877388
        ],
        [
          1500,
          0.5898588299751282
        ],
        [
          2000,
          0.5860008597373962
        ],
        [
          2500,
          0.5891122221946716
        ],
        [
          3000,
          0.5957652926445007
        ],
        [
          3500,
          0.6035293340682983
        ],
        [
          4000,
          0.6105637550354004
        ],
        [
          4500,
          0.6179798245429993
        ],
        [
          5000,
          0.6435525417327881
        ],
        [
          5500,
          0.6674255132675171
        ],
        [
          6000,
          0.6485549211502075
        ],
        [
          6500,
          0.6165245771408081
        ],
        [
          7000,
          0.6047284603118896
        ],
        [
          7500,
          0.5925395488739014
        ],
        [
          8000,
          0.5918838381767273
        ],
        [
          8500,
          0.6043602228164673
        ],
        [
          9000,
          0.6107036471366882
        ],
        [
          9500,
          0.6128381490707397
        ],
        [
          10000,
          0.6133909821510315
        ],
        [
          10500,
          0.6139271855354309
        ],
        [
          11000,
          0.6167520880699158
        ],
        [
          11500,
          0.6180985569953918
        ],
        [
          12000,
          0.6231808662414551
        ],
        [
          12500,
          0.618798553943634
        ],
        [
          13000,
          0.617444634437561
        ],
        [
          13500,
          0.6170821189880371
        ],
        [
          14000,
          0.6173112988471985
        ],
        [
          14500,
          0.6160362362861633
        ],
        [
          15000,
          0.6160516142845154
        ],
        [
          15500,
          0.6159706711769104
        ],
        [
          16000,
          0.6165083050727844
        ],
        [
          16500,
          0.6178243160247803
        ],
        [
          17000,
          0.6147275567054749
        ],
        [
          17500,
          0.61715167760849
        ],
        [
          18000,
          0.6158509254455566
        ],
        [
          18500,
          0.6189199090003967
        ],
        [
          19000,
          0.6128987073898315
        ],
        [
          19500,
          0.6152046918869019
        ],
        [
          20000,
          0.614423394203186
        ],
        [
          20500,
          0.6113772392272949
        ],
        [
          21000,
          0.6160185933113098
        ],
        [
          21500,
          0.6153258681297302
        ],
        [
          22000,
          0.6144042611122131
        ],
        [
          22500,
          0.615700364112854
        ],
        [
          23000,
          0.6160382628440857
        ],
        [
          23500,
          0.6153897047042847
        ],
        [
          24000,
          0.6158640384674072
        ],
        [
          24500,
          0.6202110052108765
        ],
        [
          25000,
          0.6167041063308716
        ],
        [
          25500,
          0.614386796951294
        ],
        [
          26000,
          0.61542147397995
        ],
        [
          26500,
          0.6148969531059265
        ],
        [
          27000,
          0.615966796875
        ],
        [
          27500,
          0.6149892807006836
        ],
        [
          28000,
          0.6179111003875732
        ],
        [
          28500,
          0.6212530732154846
        ],
        [
          29000,
          0.6171910762786865
        ],
        [
          29500,
          0.6168073415756226
        ],
        [
          30000,
          0.6183841228485107
        ],
        [
          30500,
          0.622188150882721
        ],
        [
          31000,
          0.6176417469978333
        ],
        [
          31500,
          0.617858350276947
        ],
        [
          32000,
          0.6171727776527405
        ],
        [
          32500,
          0.6167894601821899
        ],
        [
          33000,
          0.616624653339386
        ]
      ]
    },
    "3": {
      "converged": true,
      "hit_cap": false,
      "trustworthy": true,
      "still_improving_at_stop": false,
      "diverged": false,
      "stop_epoch": 33000,
      "best_val": 0.06399741768836975,
      "best_epoch": 27000,
      "recent_improvement": -0.0001674070954322815,
      "trajectory": [
        [
          500,
          0.6794300079345703
        ],
        [
          1000,
          0.6347692608833313
        ],
        [
          1500,
          0.5752155184745789
        ],
        [
          2000,
          0.5701116919517517
        ],
        [
          2500,
          0.560407280921936
        ],
        [
          3000,
          0.532244086265564
        ],
        [
          3500,
          0.5018641948699951
        ],
        [
          4000,
          0.4922763705253601
        ],
        [
          4500,
          0.49621158838272095
        ],
        [
          5000,
          0.4862048327922821
        ],
        [
          5500,
          0.47876855731010437
        ],
        [
          6000,
          0.4739461839199066
        ],
        [
          6500,
          0.44903919100761414
        ],
        [
          7000,
          0.4319136440753937
        ],
        [
          7500,
          0.4137652516365051
        ],
        [
          8000,
          0.38592544198036194
        ],
        [
          8500,
          0.34253615140914917
        ],
        [
          9000,
          0.2909165024757385
        ],
        [
          9500,
          0.2568712830543518
        ],
        [
          10000,
          0.22150886058807373
        ],
        [
          10500,
          0.18767817318439484
        ],
        [
          11000,
          0.16329456865787506
        ],
        [
          11500,
          0.1300620138645172
        ],
        [
          12000,
          0.11420445889234543
        ],
        [
          12500,
          0.1034177616238594
        ],
        [
          13000,
          0.09191649407148361
        ],
        [
          13500,
          0.09097806364297867
        ],
        [
          14000,
          0.08649922907352448
        ],
        [
          14500,
          0.08261099457740784
        ],
        [
          15000,
          0.0779733657836914
        ],
        [
          15500,
          0.07760359346866608
        ],
        [
          16000,
          0.07318060100078583
        ],
        [
          16500,
          0.07485846430063248
        ],
        [
          17000,
          0.071271151304245
        ],
        [
          17500,
          0.07496081292629242
        ],
        [
          18000,
          0.07073066383600235
        ],
        [
          18500,
          0.07616405189037323
        ],
        [
          19000,
          0.07224307209253311
        ],
        [
          19500,
          0.06841319799423218
        ],
        [
          20000,
          0.06641342490911484
        ],
        [
          20500,
          0.07350136339664459
        ],
        [
          21000,
          0.06820197403430939
        ],
        [
          21500,
          0.06765966862440109
        ],
        [
          22000,
          0.06661246716976166
        ],
        [
          22500,
          0.06762277334928513
        ],
        [
          23000,
          0.06606176495552063
        ],
        [
          23500,
          0.0655350387096405
        ],
        [
          24000,
          0.0669238418340683
        ],
        [
          24500,
          0.06545541435480118
        ],
        [
          25000,
          0.0645400732755661
        ],
        [
          25500,
          0.06665319949388504
        ],
        [
          26000,
          0.06418058276176453
        ],
        [
          26500,
          0.06558635830879211
        ],
        [
          27000,
          0.06399741768836975
        ],
        [
          27500,
          0.06661946326494217
        ],
        [
          28000,
          0.06520945578813553
        ],
        [
          28500,
          0.0653998851776123
        ],
        [
          29000,
          0.06411202996969223
        ],
        [
          29500,
          0.07023115456104279
        ],
        [
          30000,
          0.06431416422128677
        ],
        [
          30500,
          0.06437823921442032
        ],
        [
          31000,
          0.06401072442531586
        ],
        [
          31500,
          0.06396466493606567
        ],
        [
          32000,
          0.06512324512004852
        ],
        [
          32500,
          0.06666010618209839
        ],
        [
          33000,
          0.06416482478380203
        ]
      ]
    },
    "4": {
      "converged": true,
      "hit_cap": false,
      "trustworthy": true,
      "still_improving_at_stop": false,
      "diverged": false,
      "stop_epoch": 23000,
      "best_val": 0.05873849242925644,
      "best_epoch": 26000,
      "recent_improvement": 0.0012387745082378387,
      "trajectory": [
        [
          500,
          0.6812520027160645
        ],
        [
          1000,
          0.6297107934951782
        ],
        [
          1500,
          0.5809731483459473
        ],
        [
          2000,
          0.5698022246360779
        ],
        [
          2500,
          0.5497649908065796
        ],
        [
          3000,
          0.5323161482810974
        ],
        [
          3500,
          0.5036709904670715
        ],
        [
          4000,
          0.49368321895599365
        ],
        [
          4500,
          0.4907882809638977
        ],
        [
          5000,
          0.48058974742889404
        ],
        [
          5500,
          0.47232162952423096
        ],
        [
          6000,
          0.4569663405418396
        ],
        [
          6500,
          0.3351650834083557
        ],
        [
          7000,
          0.22521847486495972
        ],
        [
          7500,
          0.18557925522327423
        ],
        [
          8000,
          0.17315243184566498
        ],
        [
          8500,
          0.15639731287956238
        ],
        [
          9000,
          0.13014481961727142
        ],
        [
          9500,
          0.11471842229366302
        ],
        [
          10000,
          0.1033574640750885
        ],
        [
          10500,
          0.09015882760286331
        ],
        [
          11000,
          0.08259531855583191
        ],
        [
          11500,
          0.07656795531511307
        ],
        [
          12000,
          0.08855520933866501
        ],
        [
          12500,
          0.07057356834411621
        ],
        [
          13000,
          0.0667494684457779
        ],
        [
          13500,
          0.06495200842618942
        ],
        [
          14000,
          0.06351464241743088
        ],
        [
          14500,
          0.06222539395093918
        ],
        [
          15000,
          0.06241568177938461
        ],
        [
          15500,
          0.061728477478027344
        ],
        [
          16000,
          0.06198154389858246
        ],
        [
          16500,
          0.06256119906902313
        ],
        [
          17000,
          0.060853030532598495
        ],
        [
          17500,
          0.06471823155879974
        ],
        [
          18000,
          0.06118641048669815
        ],
        [
          18500,
          0.06308543682098389
        ],
        [
          19000,
          0.06000642105937004
        ],
        [
          19500,
          0.06009872257709503
        ],
        [
          20000,
          0.06041635572910309
        ],
        [
          20500,
          0.06025154888629913
        ],
        [
          21000,
          0.06080823764204979
        ],
        [
          21500,
          0.060322437435388565
        ],
        [
          22000,
          0.06019210070371628
        ],
        [
          22500,
          0.060546766966581345
        ],
        [
          23000,
          0.06005552411079407
        ],
        [
          23500,
          0.05973216891288757
        ],
        [
          24000,
          0.059613633900880814
        ],
        [
          24500,
          0.06236153841018677
        ],
        [
          25000,
          0.05946981906890869
        ],
        [
          25500,
          0.05915791913866997
        ],
        [
          26000,
          0.05873849242925644
        ],
        [
          26500,
          0.06071041151881218
        ],
        [
          27000,
          0.05886661633849144
        ],
        [
          27500,
          0.058612704277038574
        ],
        [
          28000,
          0.05889996886253357
        ],
        [
          28500,
          0.06059718504548073
        ],
        [
          29000,
          0.058476630598306656
        ],
        [
          29500,
          0.05945564806461334
        ],
        [
          30000,
          0.058332812041044235
        ],
        [
          30500,
          0.06460532546043396
        ],
        [
          31000,
          0.05812811478972435
        ],
        [
          31500,
          0.05794307589530945
        ],
        [
          32000,
          0.05754802003502846
        ],
        [
          32500,
          0.06027151271700859
        ],
        [
          33000,
          0.0576278418302536
        ]
      ]
    },
    "5": {
      "converged": true,
      "hit_cap": false,
      "trustworthy": true,
      "still_improving_at_stop": false,
      "diverged": false,
      "stop_epoch": 20000,
      "best_val": 0.05652964115142822,
      "best_epoch": 28000,
      "recent_improvement": -2.644956111907959e-06,
      "trajectory": [
        [
          500,
          0.6623939871788025
        ],
        [
          1000,
          0.6405795812606812
        ],
        [
          1500,
          0.5860282778739929
        ],
        [
          2000,
          0.5611233115196228
        ],
        [
          2500,
          0.5467968583106995
        ],
        [
          3000,
          0.535332977771759
        ],
        [
          3500,
          0.5109744668006897
        ],
        [
          4000,
          0.4963543713092804
        ],
        [
          4500,
          0.487755686044693
        ],
        [
          5000,
          0.4787962734699249
        ],
        [
          5500,
          0.4352840185165405
        ],
        [
          6000,
          0.3363148868083954
        ],
        [
          6500,
          0.2547663748264313
        ],
        [
          7000,
          0.19855546951293945
        ],
        [
          7500,
          0.16783295571804047
        ],
        [
          8000,
          0.15301336348056793
        ],
        [
          8500,
          0.1368546038866043
        ],
        [
          9000,
          0.1191641241312027
        ],
        [
          9500,
          0.10544545203447342
        ],
        [
          10000,
          0.0944686084985733
        ],
        [
          10500,
          0.0873091071844101
        ],
        [
          11000,
          0.08133102208375931
        ],
        [
          11500,
          0.07229673117399216
        ],
        [
          12000,
          0.07107574492692947
        ],
        [
          12500,
          0.06636127829551697
        ],
        [
          13000,
          0.06362772732973099
        ],
        [
          13500,
          0.062362123280763626
        ],
        [
          14000,
          0.06110212951898575
        ],
        [
          14500,
          0.06020643934607506
        ],
        [
          15000,
          0.060101915150880814
        ],
        [
          15500,
          0.06004880368709564
        ],
        [
          16000,
          0.0595882423222065
        ],
        [
          16500,
          0.06061674281954765
        ],
        [
          17000,
          0.060850195586681366
        ],
        [
          17500,
          0.06514264643192291
        ],
        [
          18000,
          0.06097136065363884
        ],
        [
          18500,
          0.06023629009723663
        ],
        [
          19000,
          0.06877229362726212
        ],
        [
          19500,
          0.061924368143081665
        ],
        [
          20000,
          0.07269348204135895
        ],
        [
          20500,
          0.061192091554403305
        ],
        [
          21000,
          0.06071839481592178
        ],
        [
          21500,
          0.06065335124731064
        ],
        [
          22000,
          0.060116373002529144
        ],
        [
          22500,
          0.059203408658504486
        ],
        [
          23000,
          0.05871996656060219
        ],
        [
          23500,
          0.06333542615175247
        ],
        [
          24000,
          0.05812642350792885
        ],
        [
          24500,
          0.0572655089199543
        ],
        [
          25000,
          0.0578799806535244
        ],
        [
          25500,
          0.06875434517860413
        ],
        [
          26000,
          0.057322222739458084
        ],
        [
          26500,
          0.05952988192439079
        ],
        [
          27000,
          0.05721714720129967
        ],
        [
          27500,
          0.05783183500170708
        ],
        [
          28000,
          0.05652964115142822
        ],
        [
          28500,
          0.05641994625329971
        ],
        [
          29000,
          0.05671070143580437
        ],
        [
          29500,
          0.059232305735349655
        ],
        [
          30000,
          0.05812661349773407
        ],
        [
          30500,
          0.05663645267486572
        ],
        [
          31000,
          0.05650943145155907
        ],
        [
          31500,
          0.05638200044631958
        ],
        [
          32000,
          0.056493669748306274
        ],
        [
          32500,
          0.05816645175218582
        ],
        [
          33000,
          0.057219792157411575
        ]
      ]
    },
    "6": {
      "converged": true,
      "hit_cap": false,
      "trustworthy": true,
      "still_improving_at_stop": false,
      "diverged": false,
      "stop_epoch": 20000,
      "best_val": 0.055340494960546494,
      "best_epoch": 20500,
      "recent_improvement": 0.0008174143731594086,
      "trajectory": [
        [
          500,
          0.6533688902854919
        ],
        [
          1000,
          0.6144094467163086
        ],
        [
          1500,
          0.6213180422782898
        ],
        [
          2000,
          0.5609150528907776
        ],
        [
          2500,
          0.5458218455314636
        ],
        [
          3000,
          0.5342151522636414
        ],
        [
          3500,
          0.5046509504318237
        ],
        [
          4000,
          0.494411826133728
        ],
        [
          4500,
          0.4881760776042938
        ],
        [
          5000,
          0.48038721084594727
        ],
        [
          5500,
          0.4234236776828766
        ],
        [
          6000,
          0.32362258434295654
        ],
        [
          6500,
          0.242832750082016
        ],
        [
          7000,
          0.19339756667613983
        ],
        [
          7500,
          0.16324204206466675
        ],
        [
          8000,
          0.14675919711589813
        ],
        [
          8500,
          0.1322377771139145
        ],
        [
          9000,
          0.10993673652410507
        ],
        [
          9500,
          0.09527350962162018
        ],
        [
          10000,
          0.0827617421746254
        ],
        [
          10500,
          0.07333751767873764
        ],
        [
          11000,
          0.07013875246047974
        ],
        [
          11500,
          0.06373906135559082
        ],
        [
          12000,
          0.06386875361204147
        ],
        [
          12500,
          0.0599285252392292
        ],
        [
          13000,
          0.05961766093969345
        ],
        [
          13500,
          0.05815771222114563
        ],
        [
          14000,
          0.05762091279029846
        ],
        [
          14500,
          0.05698207765817642
        ],
        [
          15000,
          0.056673500686883926
        ],
        [
          15500,
          0.057137757539749146
        ],
        [
          16000,
          0.057159651070833206
        ],
        [
          16500,
          0.05667160078883171
        ],
        [
          17000,
          0.05621352046728134
        ],
        [
          17500,
          0.06004050746560097
        ],
        [
          18000,
          0.056759096682071686
        ],
        [
          18500,
          0.056870002299547195
        ],
        [
          19000,
          0.06679967045783997
        ],
        [
          19500,
          0.05576491728425026
        ],
        [
          20000,
          0.06395720690488815
        ],
        [
          20500,
          0.055340494960546494
        ],
        [
          21000,
          0.055781975388526917
        ],
        [
          21500,
          0.05501321703195572
        ],
        [
          22000,
          0.05619106441736221
        ],
        [
          22500,
          0.05533028766512871
        ],
        [
          23000,
          0.055536288768053055
        ],
        [
          23500,
          0.05666068568825722
        ],
        [
          24000,
          0.05514153838157654
        ],
        [
          24500,
          0.05664614215493202
        ],
        [
          25000,
          0.05462227016687393
        ],
        [
          25500,
          0.05758901685476303
        ],
        [
          26000,
          0.054531171917915344
        ],
        [
          26500,
          0.055051982402801514
        ],
        [
          27000,
          0.05440207198262215
        ],
        [
          27500,
          0.05436980724334717
        ],
        [
          28000,
          0.05506661906838417
        ],
        [
          28500,
          0.05572904646396637
        ],
        [
          29000,
          0.05443987622857094
        ],
        [
          29500,
          0.055435407906770706
        ],
        [
          30000,
          0.05467202514410019
        ],
        [
          30500,
          0.054604873061180115
        ],
        [
          31000,
          0.054062701761722565
        ],
        [
          31500,
          0.05437798798084259
        ],
        [
          32000,
          0.05365099012851715
        ],
        [
          32500,
          0.05746544525027275
        ],
        [
          33000,
          0.05358465760946274
        ]
      ]
    },
    "7": {
      "converged": true,
      "hit_cap": false,
      "trustworthy": true,
      "still_improving_at_stop": false,
      "diverged": false,
      "stop_epoch": 19000,
      "best_val": 0.05623134598135948,
      "best_epoch": 26500,
      "recent_improvement": 0.00046458467841148376,
      "trajectory": [
        [
          500,
          0.6463543772697449
        ],
        [
          1000,
          0.6165803074836731
        ],
        [
          1500,
          0.5974569916725159
        ],
        [
          2000,
          0.5608130097389221
        ],
        [
          2500,
          0.5437951683998108
        ],
        [
          3000,
          0.529270350933075
        ],
        [
          3500,
          0.5085049867630005
        ],
        [
          4000,
          0.4829241931438446
        ],
        [
          4500,
          0.43937936425209045
        ],
        [
          5000,
          0.40184617042541504
        ],
        [
          5500,
          0.31621527671813965
        ],
        [
          6000,
          0.2616756558418274
        ],
        [
          6500,
          0.2347596287727356
        ],
        [
          7000,
          0.19470147788524628
        ],
        [
          7500,
          0.15695571899414062
        ],
        [
          8000,
          0.1391349732875824
        ],
        [
          8500,
          0.12835800647735596
        ],
        [
          9000,
          0.10717058926820755
        ],
        [
          9500,
          0.09699179977178574
        ],
        [
          10000,
          0.08582066744565964
        ],
        [
          10500,
          0.07858308404684067
        ],
        [
          11000,
          0.07429265975952148
        ],
        [
          11500,
          0.06826417148113251
        ],
        [
          12000,
          0.06766100972890854
        ],
        [
          12500,
          0.06377378851175308
        ],
        [
          13000,
          0.06149544566869736
        ],
        [
          13500,
          0.06114989519119263
        ],
        [
          14000,
          0.06107109785079956
        ],
        [
          14500,
          0.06105104461312294
        ],
        [
          15000,
          0.06095784530043602
        ],
        [
          15500,
          0.060672029852867126
        ],
        [
          16000,
          0.06227361038327217
        ],
        [
          16500,
          0.06048468127846718
        ],
        [
          17000,
          0.05999670550227165
        ],
        [
          17500,
          0.06922551989555359
        ],
        [
          18000,
          0.05992594361305237
        ],
        [
          18500,
          0.06160822510719299
        ],
        [
          19000,
          0.06486880034208298
        ],
        [
          19500,
          0.05852797254920006
        ],
        [
          20000,
          0.07933207601308823
        ],
        [
          20500,
          0.05975176393985748
        ],
        [
          21000,
          0.058746013790369034
        ],
        [
          21500,
          0.05696985870599747
        ],
        [
          22000,
          0.057156942784786224
        ],
        [
          22500,
          0.057371482253074646
        ],
        [
          23000,
          0.05782452970743179
        ],
        [
          23500,
          0.057739753276109695
        ],
        [
          24000,
          0.05716240406036377
        ],
        [
          24500,
          0.06025213748216629
        ],
        [
          25000,
          0.05681275576353073
        ],
        [
          25500,
          0.0606587678194046
        ],
        [
          26000,
          0.05706079304218292
        ],
        [
          26500,
          0.05623134598135948
        ],
        [
          27000,
          0.057014547288417816
        ],
        [
          27500,
          0.05686832591891289
        ],
        [
          28000,
          0.05695025250315666
        ],
        [
          28500,
          0.05909234285354614
        ],
        [
          29000,
          0.05732675641775131
        ],
        [
          29500,
          0.06004134565591812
        ],
        [
          30000,
          0.05791936069726944
        ],
        [
          30500,
          0.06009950488805771
        ],
        [
          31000,
          0.057518526911735535
        ],
        [
          31500,
          0.05823291093111038
        ],
        [
          32000,
          0.056811243295669556
        ],
        [
          32500,
          0.059591326862573624
        ],
        [
          33000,
          0.05654996261000633
        ]
      ]
    },
    "8": {
      "converged": true,
      "hit_cap": false,
      "trustworthy": true,
      "still_improving_at_stop": false,
      "diverged": false,
      "stop_epoch": 24500,
      "best_val": 0.05170540139079094,
      "best_epoch": 30500,
      "recent_improvement": 0.0015145093202590942,
      "trajectory": [
        [
          500,
          0.6372965574264526
        ],
        [
          1000,
          0.5809448957443237
        ],
        [
          1500,
          0.5557262897491455
        ],
        [
          2000,
          0.5436645746231079
        ],
        [
          2500,
          0.5290279388427734
        ],
        [
          3000,
          0.45894068479537964
        ],
        [
          3500,
          0.3523563742637634
        ],
        [
          4000,
          0.3040749430656433
        ],
        [
          4500,
          0.2598867416381836
        ],
        [
          5000,
          0.26558801531791687
        ],
        [
          5500,
          0.2251548022031784
        ],
        [
          6000,
          0.1623896211385727
        ],
        [
          6500,
          0.12981721758842468
        ],
        [
          7000,
          0.10152968764305115
        ],
        [
          7500,
          0.08322332054376602
        ],
        [
          8000,
          0.07932640612125397
        ],
        [
          8500,
          0.07490604370832443
        ],
        [
          9000,
          0.06933874636888504
        ],
        [
          9500,
          0.06593216210603714
        ],
        [
          10000,
          0.06393954157829285
        ],
        [
          10500,
          0.06304154545068741
        ],
        [
          11000,
          0.06192613020539284
        ],
        [
          11500,
          0.060305412858724594
        ],
        [
          12000,
          0.06011977419257164
        ],
        [
          12500,
          0.058207690715789795
        ],
        [
          13000,
          0.05820922181010246
        ],
        [
          13500,
          0.057091038674116135
        ],
        [
          14000,
          0.05666271969676018
        ],
        [
          14500,
          0.056116439402103424
        ],
        [
          15000,
          0.05602364242076874
        ],
        [
          15500,
          0.05524506792426109
        ],
        [
          16000,
          0.05543076992034912
        ],
        [
          16500,
          0.05451124161481857
        ],
        [
          17000,
          0.05456998944282532
        ],
        [
          17500,
          0.06806974112987518
        ],
        [
          18000,
          0.05425337329506874
        ],
        [
          18500,
          0.053855400532484055
        ],
        [
          19000,
          0.060648027807474136
        ],
        [
          19500,
          0.053772829473018646
        ],
        [
          20000,
          0.06937208026647568
        ],
        [
          20500,
          0.05423152446746826
        ],
        [
          21000,
          0.05296526476740837
        ],
        [
          21500,
          0.05307018756866455
        ],
        [
          22000,
          0.052937544882297516
        ],
        [
          22500,
          0.053279291838407516
        ],
        [
          23000,
          0.05352284759283066
        ],
        [
          23500,
          0.058822210878133774
        ],
        [
          24000,
          0.052813734859228134
        ],
        [
          24500,
          0.05352083221077919
        ],
        [
          25000,
          0.05222681537270546
        ],
        [
          25500,
          0.05373947322368622
        ],
        [
          26000,
          0.05244794860482216
        ],
        [
          26500,
          0.05237491428852081
        ],
        [
          27000,
          0.05261439457535744
        ],
        [
          27500,
          0.05258719250559807
        ],
        [
          28000,
          0.052069779485464096
        ],
        [
          28500,
          0.052873045206069946
        ],
        [
          29000,
          0.05258670821785927
        ],
        [
          29500,
          0.05748029053211212
        ],
        [
          30000,
          0.05275624617934227
        ],
        [
          30500,
          0.05170540139079094
        ],
        [
          31000,
          0.05233490467071533
        ],
        [
          31500,
          0.052376456558704376
        ],
        [
          32000,
          0.0527852438390255
        ],
        [
          32500,
          0.05431528016924858
        ],
        [
          33000,
          0.05109988525509834
        ]
      ]
    },
    "9": {
      "converged": true,
      "hit_cap": false,
      "trustworthy": true,
      "still_improving_at_stop": false,
      "diverged": false,
      "stop_epoch": 12000,
      "best_val": 0.05503271892666817,
      "best_epoch": 6000,
      "recent_improvement": -0.0007694251835346222,
      "trajectory": [
        [
          500,
          0.6121101975440979
        ],
        [
          1000,
          0.45637571811676025
        ],
        [
          1500,
          0.41591426730155945
        ],
        [
          2000,
          0.4158550202846527
        ],
        [
          2500,
          0.40187716484069824
        ],
        [
          3000,
          0.3965437114238739
        ],
        [
          3500,
          0.22829879820346832
        ],
        [
          4000,
          0.11655230075120926
        ],
        [
          4500,
          0.07809654623270035
        ],
        [
          5000,
          0.06484778225421906
        ],
        [
          5500,
          0.060348257422447205
        ],
        [
          6000,
          0.05503271892666817
        ],
        [
          6500,
          0.053077470511198044
        ],
        [
          7000,
          0.058110713958740234
        ],
        [
          7500,
          0.06008375808596611
        ],
        [
          8000,
          0.062071140855550766
        ],
        [
          8500,
          0.06307391822338104
        ],
        [
          9000,
          0.06319132447242737
        ],
        [
          9500,
          0.06155886501073837
        ],
        [
          10000,
          0.059706613421440125
        ],
        [
          10500,
          0.0615149550139904
        ],
        [
          11000,
          0.06018320843577385
        ],
        [
          11500,
          0.059750996530056
        ],
        [
          12000,
          0.059656646102666855
        ],
        [
          12500,
          0.06028592586517334
        ],
        [
          13000,
          0.06049510836601257
        ],
        [
          13500,
          0.06305506825447083
        ],
        [
          14000,
          0.06322378665208817
        ],
        [
          14500,
          0.06430094689130783
        ],
        [
          15000,
          0.06628526002168655
        ],
        [
          15500,
          0.06257800757884979
        ],
        [
          16000,
          0.060796745121479034
        ],
        [
          16500,
          0.05960773304104805
        ],
        [
          17000,
          0.05912160128355026
        ],
        [
          17500,
          0.07978031784296036
        ],
        [
          18000,
          0.058211300522089005
        ],
        [
          18500,
          0.05731525272130966
        ],
        [
          19000,
          0.07168707251548767
        ],
        [
          19500,
          0.057216543704271317
        ],
        [
          20000,
          0.06970751285552979
        ],
        [
          20500,
          0.05796634778380394
        ],
        [
          21000,
          0.05770079419016838
        ],
        [
          21500,
          0.05696245655417442
        ],
        [
          22000,
          0.058176420629024506
        ],
        [
          22500,
          0.05708298459649086
        ],
        [
          23000,
          0.056589093059301376
        ],
        [
          23500,
          0.058071453124284744
        ],
        [
          24000,
          0.05652109906077385
        ],
        [
          24500,
          0.057990290224552155
        ],
        [
          25000,
          0.056786492466926575
        ],
        [
          25500,
          0.056856948882341385
        ],
        [
          26000,
          0.0558592863380909
        ],
        [
          26500,
          0.0575280524790287
        ],
        [
          27000,
          0.05570606142282486
        ],
        [
          27500,
          0.05730465054512024
        ],
        [
          28000,
          0.05641268566250801
        ],
        [
          28500,
          0.056150730699300766
        ],
        [
          29000,
          0.0558747872710228
        ],
        [
          29500,
          0.060410987585783005
        ],
        [
          30000,
          0.05592983216047287
        ],
        [
          30500,
          0.05623498931527138
        ],
        [
          31000,
          0.05586869642138481
        ],
        [
          31500,
          0.05558392032980919
        ],
        [
          32000,
          0.05559232831001282
        ],
        [
          32500,
          0.06089238449931145
        ],
        [
          33000,
          0.05647548660635948
        ]
      ]
    },
    "10": {
      "converged": true,
      "hit_cap": false,
      "trustworthy": true,
      "still_improving_at_stop": false,
      "diverged": false,
      "stop_epoch": 12500,
      "best_val": 0.039902329444885254,
      "best_epoch": 31500,
      "recent_improvement": 0.004400096833705902,
      "trajectory": [
        [
          500,
          0.6183987259864807
        ],
        [
          1000,
          0.3635422885417938
        ],
        [
          1500,
          0.20327936112880707
        ],
        [
          2000,
          0.12946262955665588
        ],
        [
          2500,
          0.10166057199239731
        ],
        [
          3000,
          0.08770883828401566
        ],
        [
          3500,
          0.07760664820671082
        ],
        [
          4000,
          0.073084756731987
        ],
        [
          4500,
          0.07306206971406937
        ],
        [
          5000,
          0.07069005072116852
        ],
        [
          5500,
          0.0721885934472084
        ],
        [
          6000,
          0.06644488126039505
        ],
        [
          6500,
          0.061527326703071594
        ],
        [
          7000,
          0.06147943437099457
        ],
        [
          7500,
          0.06269749999046326
        ],
        [
          8000,
          0.0648181289434433
        ],
        [
          8500,
          0.0654645711183548
        ],
        [
          9000,
          0.06706114113330841
        ],
        [
          9500,
          0.06597674638032913
        ],
        [
          10000,
          0.06505484879016876
        ],
        [
          10500,
          0.06349972635507584
        ],
        [
          11000,
          0.06347467005252838
        ],
        [
          11500,
          0.06274225562810898
        ],
        [
          12000,
          0.0634024441242218
        ],
        [
          12500,
          0.06160390377044678
        ],
        [
          13000,
          0.06170252338051796
        ],
        [
          13500,
          0.06125898286700249
        ],
        [
          14000,
          0.06083377078175545
        ],
        [
          14500,
          0.0602283738553524
        ],
        [
          15000,
          0.05894291400909424
        ],
        [
          15500,
          0.05609942600131035
        ],
        [
          16000,
          0.054652951657772064
        ],
        [
          16500,
          0.05284705385565758
        ],
        [
          17000,
          0.0516374446451664
        ],
        [
          17500,
          0.058341726660728455
        ],
        [
          18000,
          0.051325857639312744
        ],
        [
          18500,
          0.05140909180045128
        ],
        [
          19000,
          0.06429111212491989
        ],
        [
          19500,
          0.049361761659383774
        ],
        [
          20000,
          0.06097148731350899
        ],
        [
          20500,
          0.04794183745980263
        ],
        [
          21000,
          0.04926852509379387
        ],
        [
          21500,
          0.04780369997024536
        ],
        [
          22000,
          0.04793498292565346
        ],
        [
          22500,
          0.04718205705285072
        ],
        [
          23000,
          0.04686165601015091
        ],
        [
          23500,
          0.04822932928800583
        ],
        [
          24000,
          0.045494988560676575
        ],
        [
          24500,
          0.046632613986730576
        ],
        [
          25000,
          0.04426830634474754
        ],
        [
          25500,
          0.046323202550411224
        ],
        [
          26000,
          0.04482721909880638
        ],
        [
          26500,
          0.042656220495700836
        ],
        [
          27000,
          0.04306502267718315
        ],
        [
          27500,
          0.04324830323457718
        ],
        [
          28000,
          0.04303639009594917
        ],
        [
          28500,
          0.043378233909606934
        ],
        [
          29000,
          0.04196152091026306
        ],
        [
          29500,
          0.044040191918611526
        ],
        [
          30000,
          0.042696040123701096
        ],
        [
          30500,
          0.045263320207595825
        ],
        [
          31000,
          0.04078437015414238
        ],
        [
          31500,
          0.039902329444885254
        ],
        [
          32000,
          0.04027675464749336
        ],
        [
          32500,
          0.04372121021151543
        ],
        [
          33000,
          0.03866492584347725
        ]
      ]
    },
    "11": {
      "converged": true,
      "hit_cap": false,
      "trustworthy": true,
      "still_improving_at_stop": false,
      "diverged": false,
      "stop_epoch": 10000,
      "best_val": 0.0352599062025547,
      "best_epoch": 26500,
      "recent_improvement": 0.0025173425674438477,
      "trajectory": [
        [
          500,
          0.6158431768417358
        ],
        [
          1000,
          0.18442955613136292
        ],
        [
          1500,
          0.07907717674970627
        ],
        [
          2000,
          0.0654643252491951
        ],
        [
          2500,
          0.06652923673391342
        ],
        [
          3000,
          0.06076484173536301
        ],
        [
          3500,
          0.05714578554034233
        ],
        [
          4000,
          0.05357088893651962
        ],
        [
          4500,
          0.054533883929252625
        ],
        [
          5000,
          0.05506236478686333
        ],
        [
          5500,
          0.058629024773836136
        ],
        [
          6000,
          0.05342264845967293
        ],
        [
          6500,
          0.053388919681310654
        ],
        [
          7000,
          0.053685545921325684
        ],
        [
          7500,
          0.05532344803214073
        ],
        [
          8000,
          0.055570874363183975
        ],
        [
          8500,
          0.05638263002038002
        ],
        [
          9000,
          0.05676006153225899
        ],
        [
          9500,
          0.05623337998986244
        ],
        [
          10000,
          0.055651817470788956
        ],
        [
          10500,
          0.058034446090459824
        ],
        [
          11000,
          0.05618443712592125
        ],
        [
          11500,
          0.05591922253370285
        ],
        [
          12000,
          0.056985411792993546
        ],
        [
          12500,
          0.055139318108558655
        ],
        [
          13000,
          0.055134810507297516
        ],
        [
          13500,
          0.05489667132496834
        ],
        [
          14000,
          0.05387864261865616
        ],
        [
          14500,
          0.05292638763785362
        ],
        [
          15000,
          0.051013145595788956
        ],
        [
          15500,
          0.047871772199869156
        ],
        [
          16000,
          0.04609018191695213
        ],
        [
          16500,
          0.04397905245423317
        ],
        [
          17000,
          0.043102335184812546
        ],
        [
          17500,
          0.043585509061813354
        ],
        [
          18000,
          0.0418824702501297
        ],
        [
          18500,
          0.041025836020708084
        ],
        [
          19000,
          0.04304571822285652
        ],
        [
          19500,
          0.040300264954566956
        ],
        [
          20000,
          0.04383480176329613
        ],
        [
          20500,
          0.03963048756122589
        ],
        [
          21000,
          0.041018448770046234
        ],
        [
          21500,
          0.038879457861185074
        ],
        [
          22000,
          0.03879252448678017
        ],
        [
          22500,
          0.0390382818877697
        ],
        [
          23000,
          0.03905739262700081
        ],
        [
          23500,
          0.04015401378273964
        ],
        [
          24000,
          0.03747355565428734
        ],
        [
          24500,
          0.03880208358168602
        ],
        [
          25000,
          0.036474455147981644
        ],
        [
          25500,
          0.0372869111597538
        ],
        [
          26000,
          0.03687809035181999
        ],
        [
          26500,
          0.0352599062025547
        ],
        [
          27000,
          0.03623497113585472
        ],
        [
          27500,
          0.03567250818014145
        ],
        [
          28000,
          0.0357966385781765
        ],
        [
          28500,
          0.03599795326590538
        ],
        [
          29000,
          0.03489171341061592
        ],
        [
          29500,
          0.03604787588119507
        ],
        [
          30000,
          0.035887718200683594
        ],
        [
          30500,
          0.040819525718688965
        ],
        [
          31000,
          0.03448254615068436
        ],
        [
          31500,
          0.03470657020807266
        ],
        [
          32000,
          0.03456965088844299
        ],
        [
          32500,
          0.035924263298511505
        ],
        [
          33000,
          0.03371762856841087
        ]
      ]
    },
    "12": {
      "converged": true,
      "hit_cap": false,
      "trustworthy": true,
      "still_improving_at_stop": false,
      "diverged": false,
      "stop_epoch": 21500,
      "best_val": 0.02899639494717121,
      "best_epoch": 15500,
      "recent_improvement": 0.0006978735327720642,
      "trajectory": [
        [
          500,
          0.6097566485404968
        ],
        [
          1000,
          0.09468558430671692
        ],
        [
          1500,
          0.06814919412136078
        ],
        [
          2000,
          0.05660371109843254
        ],
        [
          2500,
          0.05750134959816933
        ],
        [
          3000,
          0.05156461149454117
        ],
        [
          3500,
          0.046626072376966476
        ],
        [
          4000,
          0.043212033808231354
        ],
        [
          4500,
          0.045599497854709625
        ],
        [
          5000,
          0.04726420342922211
        ],
        [
          5500,
          0.043933574110269547
        ],
        [
          6000,
          0.04140539467334747
        ],
        [
          6500,
          0.04203065112233162
        ],
        [
          7000,
          0.04340449720621109
        ],
        [
          7500,
          0.043334074318408966
        ],
        [
          8000,
          0.04212449863553047
        ],
        [
          8500,
          0.04173078387975693
        ],
        [
          9000,
          0.04149169474840164
        ],
        [
          9500,
          0.04084041342139244
        ],
        [
          10000,
          0.0396851971745491
        ],
        [
          10500,
          0.039956703782081604
        ],
        [
          11000,
          0.039154648780822754
        ],
        [
          11500,
          0.03841876983642578
        ],
        [
          12000,
          0.038210317492485046
        ],
        [
          12500,
          0.03730565309524536
        ],
        [
          13000,
          0.03651638701558113
        ],
        [
          13500,
          0.034966208040714264
        ],
        [
          14000,
          0.0342705100774765
        ],
        [
          14500,
          0.03253444656729698
        ],
        [
          15000,
          0.030926857143640518
        ],
        [
          15500,
          0.02899639494717121
        ],
        [
          16000,
          0.028794564306735992
        ],
        [
          16500,
          0.02749810926616192
        ],
        [
          17000,
          0.027398649603128433
        ],
        [
          17500,
          0.028548838570713997
        ],
        [
          18000,
          0.028197050094604492
        ],
        [
          18500,
          0.02749454416334629
        ],
        [
          19000,
          0.03098832070827484
        ],
        [
          19500,
          0.028186533600091934
        ],
        [
          20000,
          0.030278101563453674
        ],
        [
          20500,
          0.029626255854964256
        ],
        [
          21000,
          0.02808964066207409
        ],
        [
          21500,
          0.028047259896993637
        ],
        [
          22000,
          0.028273245319724083
        ],
        [
          22500,
          0.028408069163560867
        ],
        [
          23000,
          0.028695659711956978
        ],
        [
          23500,
          0.03198599815368652
        ],
        [
          24000,
          0.028225354850292206
        ],
        [
          24500,
          0.028360532596707344
        ],
        [
          25000,
          0.028107067570090294
        ],
        [
          25500,
          0.030312925577163696
        ],
        [
          26000,
          0.02817120961844921
        ],
        [
          26500,
          0.027821725234389305
        ],
        [
          27000,
          0.02844958007335663
        ],
        [
          27500,
          0.02804376557469368
        ],
        [
          28000,
          0.029197270050644875
        ],
        [
          28500,
          0.02869517356157303
        ],
        [
          29000,
          0.028084268793463707
        ],
        [
          29500,
          0.027953103184700012
        ],
        [
          30000,
          0.027604786679148674
        ],
        [
          30500,
          0.04359191283583641
        ],
        [
          31000,
          0.027847371995449066
        ],
        [
          31500,
          0.028342103585600853
        ],
        [
          32000,
          0.02801588922739029
        ],
        [
          32500,
          0.030192704871296883
        ],
        [
          33000,
          0.027751706540584564
        ]
      ]
    }
  },
  "n_widths_trustworthy": 12,
  "all_widths_trustworthy": true,
  "hit_cap": false,
  "train_wall_clock_s": 70.53817384596914,
  "steps_to_converge": 33000,
  "params_allocated": 180,
  "params_effective": 78,
  "executed_flops_by_width": {
    "1": 2,
    "2": 4,
    "3": 6,
    "4": 8,
    "5": 10,
    "6": 12,
    "7": 14,
    "8": 16,
    "9": 18,
    "10": 20,
    "11": 22,
    "12": 24
  },
  "train_mse_by_width": {
    "1": 0.9220016598701477,
    "2": 0.6515706777572632,
    "3": 0.06312264502048492,
    "4": 0.060531966388225555,
    "5": 0.059404537081718445,
    "6": 0.05426698178052902,
    "7": 0.05534331128001213,
    "8": 0.05365936458110809,
    "9": 0.057683154940605164,
    "10": 0.032918963581323624,
    "11": 0.03044717200100422,
    "12": 0.02486395463347435
  },
  "heldout_mse_by_width": {
    "1": 0.961491048336029,
    "2": 0.6666314005851746,
    "3": 0.0672648549079895,
    "4": 0.06772643327713013,
    "5": 0.06499039381742477,
    "6": 0.056972257792949677,
    "7": 0.05740368738770485,
    "8": 0.05650399625301361,
    "9": 0.06148558482527733,
    "10": 0.03865102306008339,
    "11": 0.03680279478430748,
    "12": 0.03005029447376728
  },
  "training_schedule": "sandwich",
  "provenance": {
    "timestamp_utc": "2026-07-22T03:02:13+00:00",
    "git": {
      "commit": "0903ab7b0fd622668ca4acff2c0d4cb6ea518afb",
      "dirty": true
    },
    "python": "3.12.13",
    "torch": "2.10.0+xpu",
    "numpy": "2.4.3",
    "platform": "Linux-7.1.3-200.fc44.x86_64-x86_64-with-glibc2.43",
    "threads": {
      "omp_num_threads": "4",
      "torch_num_threads": 4,
      "cpu_count": 22
    },
    "automl_device": "cpu"
  }
}